{
    "type": "Feature",
    "geometry": {
        "type": "Point",
        "coordinates": [
            -143.24138888888888,
            61.74944444444444
        ]
    },
    "properties": {
        "feet": null,
        "meters": null,
        "latitude": 61.74944444444444,
        "longitude": -143.24138888888888,
        "name": "Atna Peaks",
        "regions": [],
        "countries": [
            "United States"
        ],
        "continent": "North America",
        "marker-size": "large",
        "marker-symbol": "triangle",
        "state": "Alaska"
    }
}