{
    "type": "Feature",
    "geometry": {
        "type": "Point",
        "coordinates": [
            -145.30055555555558,
            61.12555555555556
        ]
    },
    "properties": {
        "feet": null,
        "meters": null,
        "latitude": 61.12555555555556,
        "longitude": -145.30055555555558,
        "name": "Cleave Peak",
        "regions": [],
        "countries": [
            "United States"
        ],
        "continent": "North America",
        "marker-size": "large",
        "marker-symbol": "triangle",
        "state": "Alaska"
    }
}