{
    "type": "Feature",
    "geometry": {
        "type": "Point",
        "coordinates": [
            -151.0063888888889,
            63.06888888888889
        ]
    },
    "properties": {
        "feet": null,
        "meters": null,
        "latitude": 63.06888888888889,
        "longitude": -151.0063888888889,
        "name": "Denali",
        "regions": [],
        "countries": [
            "United States"
        ],
        "continent": "North America",
        "marker-size": "large",
        "marker-symbol": "triangle",
        "state": "Alaska"
    }
}