{
    "type": "Feature",
    "geometry": {
        "type": "Point",
        "coordinates": [
            -159.32416666666666,
            60.115833333333335
        ]
    },
    "properties": {
        "feet": null,
        "meters": null,
        "latitude": 60.115833333333335,
        "longitude": -159.32416666666666,
        "name": "Dillingham High Point",
        "regions": [],
        "countries": [
            "United States"
        ],
        "continent": "North America",
        "marker-size": "large",
        "marker-symbol": "triangle",
        "state": "Alaska"
    }
}