{
    "type": "Feature",
    "geometry": {
        "type": "Point",
        "coordinates": [
            -132.32527777777779,
            56.11972222222222
        ]
    },
    "properties": {
        "feet": null,
        "meters": null,
        "latitude": 56.11972222222222,
        "longitude": -132.32527777777779,
        "name": "Etolin Island High Point",
        "regions": [],
        "countries": [
            "United States"
        ],
        "continent": "North America",
        "marker-size": "large",
        "marker-symbol": "triangle",
        "state": "Alaska"
    }
}