{
    "type": "Feature",
    "geometry": {
        "type": "Point",
        "coordinates": [
            -178.7938888888889,
            51.78805555555555
        ]
    },
    "properties": {
        "feet": null,
        "meters": null,
        "latitude": 51.78805555555555,
        "longitude": -178.7938888888889,
        "name": "Gareloi Volcano",
        "regions": [],
        "countries": [
            "United States"
        ],
        "continent": "North America",
        "marker-size": "large",
        "marker-symbol": "triangle",
        "state": "Alaska"
    }
}