{
  "type": "Feature",
  "geometry": {
    "type": "Point",
    "coordinates": [
      -154.173889,
      61.659084
    ]
  },
  "properties": {
    "feet": 8107,
    "meters": 2471,
    "latitude": 61.659084,
    "longitude": -154.173889,
    "name": "Golgotha",
    "regions": [
      "Alaska/Yukon Ranges",
      "Alaska Range"
    ],
    "states": [
      "Alaska"
    ],
    "countries": [
      "United States"
    ],
    "continent": "North America",
    "marker-size": "medium",
    "marker-symbol": "triangle"
  }
}
