{
    "type": "Feature",
    "geometry": {
        "type": "Point",
        "coordinates": [
            -141.35083333333333,
            61.134166666666665
        ]
    },
    "properties": {
        "feet": null,
        "meters": null,
        "latitude": 61.134166666666665,
        "longitude": -141.35083333333333,
        "name": "Mount Donna",
        "regions": [],
        "countries": [
            "United States"
        ],
        "continent": "North America",
        "marker-size": "large",
        "marker-symbol": "triangle",
        "state": "Alaska"
    }
}