{
    "type": "Feature",
    "geometry": {
        "type": "Point",
        "coordinates": [
            -141.3138888888889,
            61.22833333333333
        ]
    },
    "properties": {
        "feet": null,
        "meters": null,
        "latitude": 61.22833333333333,
        "longitude": -141.3138888888889,
        "name": "Mount Gunnar Naslund",
        "regions": [],
        "countries": [
            "United States"
        ],
        "continent": "North America",
        "marker-size": "large",
        "marker-symbol": "triangle",
        "state": "Alaska"
    }
}