{
    "type": "Feature",
    "geometry": {
        "type": "Point",
        "coordinates": [
            -137.1711111111111,
            58.6625
        ]
    },
    "properties": {
        "feet": null,
        "meters": null,
        "latitude": 58.6625,
        "longitude": -137.1711111111111,
        "name": "Mount Crillon",
        "regions": [],
        "countries": [
            "United States"
        ],
        "continent": "North America",
        "marker-size": "large",
        "marker-symbol": "triangle",
        "state": "Alaska"
    }
}