{
    "type": "Feature",
    "geometry": {
        "type": "Point",
        "coordinates": [
            -176.7408333333333,
            51.936388888888885
        ]
    },
    "properties": {
        "feet": null,
        "meters": null,
        "latitude": 51.936388888888885,
        "longitude": -176.7408333333333,
        "name": "Mount Moffett",
        "regions": [],
        "countries": [
            "United States"
        ],
        "continent": "North America",
        "marker-size": "large",
        "marker-symbol": "triangle",
        "state": "Alaska"
    }
}