{
    "type": "Feature",
    "geometry": {
        "type": "Point",
        "coordinates": [
            -153.39583333333331,
            60.79805555555556
        ]
    },
    "properties": {
        "feet": null,
        "meters": null,
        "latitude": 60.79805555555556,
        "longitude": -153.39583333333331,
        "name": "Mount Neacola",
        "regions": [],
        "countries": [
            "United States"
        ],
        "continent": "North America",
        "marker-size": "large",
        "marker-symbol": "triangle",
        "state": "Alaska"
    }
}