{
    "type": "Feature",
    "geometry": {
        "type": "Point",
        "coordinates": [
            -144.64194444444445,
            63.23888888888889
        ]
    },
    "properties": {
        "feet": null,
        "meters": null,
        "latitude": 63.23888888888889,
        "longitude": -144.64194444444445,
        "name": "Mount Kimball",
        "regions": [],
        "countries": [
            "United States"
        ],
        "continent": "North America",
        "marker-size": "large",
        "marker-symbol": "triangle",
        "state": "Alaska"
    }
}