{
    "type": "Feature",
    "geometry": {
        "type": "Point",
        "coordinates": [
            -132.87722222222223,
            55.53722222222222
        ]
    },
    "properties": {
        "feet": null,
        "meters": null,
        "latitude": 55.53722222222222,
        "longitude": -132.87722222222223,
        "name": "Prince of Wales Island High Point",
        "regions": [],
        "countries": [
            "United States"
        ],
        "continent": "North America",
        "marker-size": "large",
        "marker-symbol": "triangle",
        "state": "Alaska"
    }
}