{
    "type": "Feature",
    "geometry": {
        "type": "Point",
        "coordinates": [
            -142.02666666666667,
            61.41027777777778
        ]
    },
    "properties": {
        "feet": null,
        "meters": null,
        "latitude": 61.41027777777778,
        "longitude": -142.02666666666667,
        "name": "The Grand Parapet",
        "regions": [],
        "countries": [
            "United States"
        ],
        "continent": "North America",
        "marker-size": "large",
        "marker-symbol": "triangle",
        "state": "Alaska"
    }
}