{
  "type": "Feature",
  "geometry": {
    "type": "Point",
    "coordinates": [
      12.755256,
      47.156893
    ]
  },
  "properties": {
    "feet": 11693,
    "meters": 3564,
    "latitude": 47.156893,
    "longitude": 12.755256,
    "name": "Grosses Wiesbachhorn",
    "regions": [
      "Eastern Alps",
      "Austrian Alps"
    ],
    "countries": [
      "Austria"
    ],
    "continent": "Europe",
    "marker-size": "medium",
    "marker-symbol": "triangle"
  }
}
