{
  "type": "Feature",
  "geometry": {
    "type": "Point",
    "coordinates": [
      11.1167,
      47.4167
    ]
  },
  "properties": {
    "feet": 8934,
    "meters": 2723,
    "latitude": 47.4167,
    "longitude": 11.1167,
    "name": "Hochwand",
    "countries": [
      "Austria"
    ],
    "continent": "Europe",
    "marker-size": "medium",
    "marker-symbol": "triangle"
  }
}
