{
    "type": "Feature",
    "geometry": {
        "type": "Point",
        "coordinates": [
            12.35139,
            47.56917
        ]
    },
    "properties": {
        "feet": null,
        "meters": null,
        "latitude": 47.56917,
        "longitude": 12.35139,
        "name": "L%C3%A4rcheck",
        "countries": [
            "Austria"
        ],
        "continent": "Europe",
        "marker-size": "medium",
        "marker-symbol": "triangle"
    }
}