{
  "type": "Feature",
  "geometry": {
    "type": "Point",
    "coordinates": [
      12.283,
      47.0204
    ]
  },
  "properties": {
    "feet": 9869,
    "meters": 3008,
    "latitude": 47.0204,
    "longitude": 12.283,
    "name": "Ochsenbug",
    "regions": [
      "Northern Alps",
      "Austrian Alps"
    ],
    "countries": [
      "Austria"
    ],
    "continent": "Europe",
    "marker-size": "medium",
    "marker-symbol": "triangle"
  }
}
