{
  "type": "Feature",
  "geometry": {
    "type": "Point",
    "coordinates": [
      13.478851,
      47.415311
    ]
  },
  "properties": {
    "feet": 5806,
    "meters": 1770,
    "latitude": 47.415311,
    "longitude": 13.478851,
    "name": "Rossbrand",
    "regions": [
      "Northern Alps",
      "Austrian Alps"
    ],
    "countries": [
      "Austria"
    ],
    "continent": "Europe",
    "marker-size": "medium",
    "marker-symbol": "triangle"
  }
}
