{
  "type": "Feature",
  "geometry": {
    "type": "Point",
    "coordinates": [
      44.75,
      42.6667
    ]
  },
  "properties": {
    "feet": 14603,
    "meters": 4451,
    "latitude": 42.6667,
    "longitude": 44.75,
    "name": "Shan",
    "regions": [
      "Caucasus Mountains",
      "Eastern Caucasus"
    ],
    "countries": [
      "Georgia"
    ],
    "continent": "Europe",
    "marker-size": "large",
    "marker-symbol": "triangle"
  }
}
