{
    "type": "Feature",
    "geometry": {
        "type": "Point",
        "coordinates": [
            -100.2325,
            24.87167
        ]
    },
    "properties": {
        "feet": 12208.00564,
        "meters": 3721.0,
        "latitude": 24.87167,
        "longitude": -100.2325,
        "name": "Cerro El Potos\u00ed",
        "countries": [
            "Mexico"
        ],
        "continent": "North America",
        "marker-size": "medium",
        "marker-symbol": "triangle",
        "states": [
            "Nuevo Le\u00f3n"
        ]
    }
}