{
    "type": "Feature",
    "geometry": {
        "type": "Point",
        "coordinates": [
            -111.5844,
            26.1064
        ]
    },
    "properties": {
        "feet": null,
        "meters": null,
        "latitude": 26.1064,
        "longitude": -111.5844,
        "name": "Cerro Giganta",
        "regions": [],
        "countries": [
            "Mexico"
        ],
        "continent": "North America",
        "marker-size": "large",
        "marker-symbol": "triangle"
    }
}