{
    "type": "Feature",
    "geometry": {
        "type": "Point",
        "coordinates": [
            -99.7589,
            19.7381
        ]
    },
    "properties": {
        "feet": null,
        "meters": null,
        "latitude": 19.7381,
        "longitude": -99.7589,
        "name": "Jocotitl\u00e1n (volcano)",
        "regions": [],
        "countries": [
            "Mexico"
        ],
        "continent": "North America",
        "marker-size": "large",
        "marker-symbol": "triangle"
    }
}