{
    "type": "Feature",
    "geometry": {
        "type": "Point",
        "coordinates": [
            -70.9978,
            19.0231
        ]
    },
    "properties": {
        "feet": null,
        "meters": null,
        "latitude": 19.0231,
        "longitude": -70.9978,
        "name": "Pico Duarte",
        "regions": [],
        "countries": [
            "Dominican Republic"
        ],
        "continent": "North America",
        "marker-size": "large",
        "marker-symbol": "triangle"
    }
}