{
    "type": "Feature",
    "geometry": {
        "type": "Point",
        "coordinates": [
            -70.99806,
            19.02306
        ]
    },
    "properties": {
        "feet": 10173.88484,
        "meters": 3101.0,
        "latitude": 19.02306,
        "longitude": -70.99806,
        "name": "Pico Duarte",
        "countries": [
            "Dominican Republic"
        ],
        "continent": "North America",
        "marker-size": "medium",
        "marker-symbol": "triangle"
    }
}