{
    "type": "Feature",
    "geometry": {
        "type": "Point",
        "coordinates": [
            -121.665,
            48.9953
        ]
    },
    "properties": {
        "feet": null,
        "meters": null,
        "latitude": 48.9953,
        "longitude": -121.665,
        "name": "American Border Peak(Tum mea hal)",
        "regions": [],
        "countries": [
            "United States"
        ],
        "continent": "North America",
        "marker-size": "large",
        "marker-symbol": "triangle",
        "states": [
            "Washington"
        ]
    }
}