{
    "type": "Feature",
    "geometry": {
        "type": "Point",
        "coordinates": [
            -122.0875,
            42.3156
        ]
    },
    "properties": {
        "feet": null,
        "meters": null,
        "latitude": 42.3156,
        "longitude": -122.0875,
        "name": "Aspen Butte",
        "regions": [],
        "countries": [
            "United States"
        ],
        "continent": "North America",
        "marker-size": "large",
        "marker-symbol": "triangle",
        "states": [
            "Oregon"
        ]
    }
}