{
    "type": "Feature",
    "geometry": {
        "type": "Point",
        "coordinates": [
            -114.6028,
            39.9717
        ]
    },
    "properties": {
        "feet": null,
        "meters": null,
        "latitude": 39.9717,
        "longitude": -114.6028,
        "name": "Becky Peak",
        "regions": [],
        "countries": [
            "United States"
        ],
        "continent": "North America",
        "marker-size": "large",
        "marker-symbol": "triangle",
        "states": [
            "Nevada"
        ]
    }
}