{
    "type": "Feature",
    "geometry": {
        "type": "Point",
        "coordinates": [
            -112.1411,
            42.7633
        ]
    },
    "properties": {
        "feet": null,
        "meters": null,
        "latitude": 42.7633,
        "longitude": -112.1411,
        "name": "Bonneville Peak",
        "regions": [],
        "countries": [
            "United States"
        ],
        "continent": "North America",
        "marker-size": "large",
        "marker-symbol": "triangle",
        "states": [
            "Idaho"
        ]
    }
}