{
    "type": "Feature",
    "geometry": {
        "type": "Point",
        "coordinates": [
            -90.69,
            37.6969
        ]
    },
    "properties": {
        "feet": null,
        "meters": null,
        "latitude": 37.6969,
        "longitude": -90.69,
        "name": "Buford Mountain",
        "regions": [],
        "countries": [
            "United States"
        ],
        "continent": "North America",
        "marker-size": "large",
        "marker-symbol": "triangle",
        "states": [
            "Missouri"
        ]
    }
}