{
    "type": "Feature",
    "geometry": {
        "type": "Point",
        "coordinates": [
            -119.7847,
            48.9575
        ]
    },
    "properties": {
        "feet": null,
        "meters": null,
        "latitude": 48.9575,
        "longitude": -119.7847,
        "name": "Chopaka Mountain",
        "regions": [],
        "countries": [
            "United States"
        ],
        "continent": "North America",
        "marker-size": "large",
        "marker-symbol": "triangle",
        "states": [
            "Washington"
        ]
    }
}