{
    "type": "Feature",
    "geometry": {
        "type": "Point",
        "coordinates": [
            -135.9528,
            59.2919
        ]
    },
    "properties": {
        "feet": null,
        "meters": null,
        "latitude": 59.2919,
        "longitude": -135.9528,
        "name": "Chunekukleik Mountain",
        "regions": [],
        "countries": [
            "United States"
        ],
        "continent": "North America",
        "marker-size": "large",
        "marker-symbol": "triangle",
        "states": [
            "Alaska"
        ]
    }
}