{
    "type": "Feature",
    "geometry": {
        "type": "Point",
        "coordinates": [
            -116.6575,
            42.9806
        ]
    },
    "properties": {
        "feet": null,
        "meters": null,
        "latitude": 42.9806,
        "longitude": -116.6575,
        "name": "Cinnabar Mountain",
        "regions": [],
        "countries": [
            "United States"
        ],
        "continent": "North America",
        "marker-size": "large",
        "marker-symbol": "triangle",
        "states": [
            "Idaho"
        ]
    }
}