{
    "type": "Feature",
    "geometry": {
        "type": "Point",
        "coordinates": [
            -105.93,
            40.6067
        ]
    },
    "properties": {
        "feet": null,
        "meters": null,
        "latitude": 40.6067,
        "longitude": -105.93,
        "name": "Clark Peak",
        "regions": [],
        "countries": [
            "United States"
        ],
        "continent": "North America",
        "marker-size": "large",
        "marker-symbol": "triangle",
        "states": [
            "Colorado"
        ]
    }
}