{
    "type": "Feature",
    "geometry": {
        "type": "Point",
        "coordinates": [
            -121.63,
            37.3467
        ]
    },
    "properties": {
        "feet": null,
        "meters": null,
        "latitude": 37.3467,
        "longitude": -121.63,
        "name": "Copernicus Peak",
        "regions": [],
        "countries": [
            "United States"
        ],
        "continent": "North America",
        "marker-size": "large",
        "marker-symbol": "triangle",
        "states": [
            "California"
        ]
    }
}