{
    "type": "Feature",
    "geometry": {
        "type": "Point",
        "coordinates": [
            -106.4919,
            37.3811
        ]
    },
    "properties": {
        "feet": null,
        "meters": null,
        "latitude": 37.3811,
        "longitude": -106.4919,
        "name": "Cornwall Mountain",
        "regions": [],
        "countries": [
            "United States"
        ],
        "continent": "North America",
        "marker-size": "large",
        "marker-symbol": "triangle",
        "states": [
            "Colorado"
        ]
    }
}