{
    "type": "Feature",
    "geometry": {
        "type": "Point",
        "coordinates": [
            -107.6628,
            39.0397
        ]
    },
    "properties": {
        "feet": null,
        "meters": null,
        "latitude": 39.0397,
        "longitude": -107.6628,
        "name": "Crater Peak",
        "regions": [],
        "countries": [
            "United States"
        ],
        "continent": "North America",
        "marker-size": "large",
        "marker-symbol": "triangle",
        "states": [
            "Colorado"
        ]
    }
}