{
    "type": "Feature",
    "geometry": {
        "type": "Point",
        "coordinates": [
            -105.1858,
            37.1225
        ]
    },
    "properties": {
        "feet": null,
        "meters": null,
        "latitude": 37.1225,
        "longitude": -105.1858,
        "name": "Culebra Peak",
        "regions": [],
        "countries": [
            "United States"
        ],
        "continent": "North America",
        "marker-size": "large",
        "marker-symbol": "triangle",
        "states": [
            "Colorado"
        ]
    }
}