{
    "type": "Feature",
    "geometry": {
        "type": "Point",
        "coordinates": [
            -151.0064,
            63.0689
        ]
    },
    "properties": {
        "feet": null,
        "meters": null,
        "latitude": 63.0689,
        "longitude": -151.0064,
        "name": "Denali",
        "regions": [],
        "countries": [
            "United States"
        ],
        "continent": "North America",
        "marker-size": "large",
        "marker-symbol": "triangle",
        "states": [
            "Alaska"
        ]
    }
}