{
    "type": "Feature",
    "geometry": {
        "type": "Point",
        "coordinates": [
            -144.8128,
            61.1606
        ]
    },
    "properties": {
        "feet": null,
        "meters": null,
        "latitude": 61.1606,
        "longitude": -144.8128,
        "name": "Dewey Peak (Alaska)",
        "regions": [],
        "countries": [
            "United States"
        ],
        "continent": "North America",
        "marker-size": "large",
        "marker-symbol": "triangle",
        "states": [
            "Alaska"
        ]
    }
}