{
    "type": "Feature",
    "geometry": {
        "type": "Point",
        "coordinates": [
            -110.2864,
            43.3472
        ]
    },
    "properties": {
        "feet": null,
        "meters": null,
        "latitude": 43.3472,
        "longitude": -110.2864,
        "name": "Doubletop Peak",
        "regions": [],
        "countries": [
            "United States"
        ],
        "continent": "North America",
        "marker-size": "large",
        "marker-symbol": "triangle",
        "states": [
            "Wyoming"
        ]
    }
}