{
    "type": "Feature",
    "geometry": {
        "type": "Point",
        "coordinates": [
            -111.5239,
            45.2981
        ]
    },
    "properties": {
        "feet": null,
        "meters": null,
        "latitude": 45.2981,
        "longitude": -111.5239,
        "name": "Fan Mountain",
        "regions": [],
        "countries": [
            "United States"
        ],
        "continent": "North America",
        "marker-size": "large",
        "marker-symbol": "triangle",
        "states": [
            "Montana"
        ]
    }
}