{
    "type": "Feature",
    "geometry": {
        "type": "Point",
        "coordinates": [
            -111.7394,
            38.6081
        ]
    },
    "properties": {
        "feet": null,
        "meters": null,
        "latitude": 38.6081,
        "longitude": -111.7394,
        "name": "Fish Lake Hightop",
        "regions": [],
        "countries": [
            "United States"
        ],
        "continent": "North America",
        "marker-size": "large",
        "marker-symbol": "triangle",
        "states": [
            "Utah"
        ]
    }
}