{
    "type": "Feature",
    "geometry": {
        "type": "Point",
        "coordinates": [
            -109.3392,
            43.9614
        ]
    },
    "properties": {
        "feet": null,
        "meters": null,
        "latitude": 43.9614,
        "longitude": -109.3392,
        "name": "Francs Peak",
        "regions": [],
        "countries": [
            "United States"
        ],
        "continent": "North America",
        "marker-size": "large",
        "marker-symbol": "triangle",
        "states": [
            "Wyoming"
        ]
    }
}