{
    "type": "Feature",
    "geometry": {
        "type": "Point",
        "coordinates": [
            -105.8175,
            39.6339
        ]
    },
    "properties": {
        "feet": null,
        "meters": null,
        "latitude": 39.6339,
        "longitude": -105.8175,
        "name": "Grays Peak",
        "regions": [],
        "countries": [
            "United States"
        ],
        "continent": "North America",
        "marker-size": "large",
        "marker-symbol": "triangle",
        "states": [
            "Colorado"
        ]
    }
}