{
    "type": "Feature",
    "geometry": {
        "type": "Point",
        "coordinates": [
            -121.4481,
            47.8161
        ]
    },
    "properties": {
        "feet": null,
        "meters": null,
        "latitude": 47.8161,
        "longitude": -121.4481,
        "name": "Gunn Peak",
        "regions": [],
        "countries": [
            "United States"
        ],
        "continent": "North America",
        "marker-size": "large",
        "marker-symbol": "triangle",
        "states": [
            "Washington"
        ]
    }
}