{
    "type": "Feature",
    "geometry": {
        "type": "Point",
        "coordinates": [
            -82.6294,
            36.8928
        ]
    },
    "properties": {
        "feet": null,
        "meters": null,
        "latitude": 36.8928,
        "longitude": -82.6294,
        "name": "High Knob",
        "regions": [],
        "countries": [
            "United States"
        ],
        "continent": "North America",
        "marker-size": "large",
        "marker-symbol": "triangle",
        "states": [
            "Virginia"
        ]
    }
}