{
    "type": "Feature",
    "geometry": {
        "type": "Point",
        "coordinates": [
            -107.2864,
            37.3081
        ]
    },
    "properties": {
        "feet": null,
        "meters": null,
        "latitude": 37.3081,
        "longitude": -107.2864,
        "name": "Horse Mountain",
        "regions": [],
        "countries": [
            "United States"
        ],
        "continent": "North America",
        "marker-size": "large",
        "marker-symbol": "triangle",
        "states": [
            "Colorado"
        ]
    }
}