{
    "type": "Feature",
    "geometry": {
        "type": "Point",
        "coordinates": [
            -113.92,
            39.8283
        ]
    },
    "properties": {
        "feet": null,
        "meters": null,
        "latitude": 39.8283,
        "longitude": -113.92,
        "name": "Ibapah Peak",
        "regions": [],
        "countries": [
            "United States"
        ],
        "continent": "North America",
        "marker-size": "large",
        "marker-symbol": "triangle",
        "states": [
            "Utah"
        ]
    }
}