{
    "type": "Feature",
    "geometry": {
        "type": "Point",
        "coordinates": [
            -153.0914,
            60.0322
        ]
    },
    "properties": {
        "feet": null,
        "meters": null,
        "latitude": 60.0322,
        "longitude": -153.0914,
        "name": "Iliamna Volcano",
        "regions": [],
        "countries": [
            "United States"
        ],
        "continent": "North America",
        "marker-size": "large",
        "marker-symbol": "triangle",
        "states": [
            "Alaska"
        ]
    }
}