{
    "type": "Feature",
    "geometry": {
        "type": "Point",
        "coordinates": [
            -118.4164,
            41.3033
        ]
    },
    "properties": {
        "feet": null,
        "meters": null,
        "latitude": 41.3033,
        "longitude": -118.4164,
        "name": "Jackson Mountain",
        "regions": [],
        "countries": [
            "United States"
        ],
        "continent": "North America",
        "marker-size": "large",
        "marker-symbol": "triangle",
        "states": [
            "Nevada"
        ]
    }
}