{
    "type": "Feature",
    "geometry": {
        "type": "Point",
        "coordinates": [
            -118.2356,
            39.5833
        ]
    },
    "properties": {
        "feet": null,
        "meters": null,
        "latitude": 39.5833,
        "longitude": -118.2356,
        "name": "Job Peak",
        "regions": [],
        "countries": [
            "United States"
        ],
        "continent": "North America",
        "marker-size": "large",
        "marker-symbol": "triangle",
        "states": [
            "Nevada"
        ]
    }
}