{
    "type": "Feature",
    "geometry": {
        "type": "Point",
        "coordinates": [
            -114.1808,
            36.2064
        ]
    },
    "properties": {
        "feet": null,
        "meters": null,
        "latitude": 36.2064,
        "longitude": -114.1808,
        "name": "Jumbo Peak",
        "regions": [],
        "countries": [
            "United States"
        ],
        "continent": "North America",
        "marker-size": "large",
        "marker-symbol": "triangle",
        "states": [
            "Nevada"
        ]
    }
}