{
    "type": "Feature",
    "geometry": {
        "type": "Point",
        "coordinates": [
            -132.045,
            57.045
        ]
    },
    "properties": {
        "feet": 10016.40452,
        "meters": 3053.0,
        "latitude": 57.045,
        "longitude": -132.045,
        "name": "Kates Needle",
        "countries": [
            "United States"
        ],
        "continent": "North America",
        "marker-size": "medium",
        "marker-symbol": "triangle"
    }
}