{
    "type": "Feature",
    "geometry": {
        "type": "Point",
        "coordinates": [
            -117.9625,
            36.7075
        ]
    },
    "properties": {
        "feet": null,
        "meters": null,
        "latitude": 36.7075,
        "longitude": -117.9625,
        "name": "Keynot Peak",
        "regions": [],
        "countries": [
            "United States"
        ],
        "continent": "North America",
        "marker-size": "large",
        "marker-symbol": "triangle",
        "states": [
            "California"
        ]
    }
}