{
    "type": "Feature",
    "geometry": {
        "type": "Point",
        "coordinates": [
            -110.3728,
            40.7764
        ]
    },
    "properties": {
        "feet": null,
        "meters": null,
        "latitude": 40.7764,
        "longitude": -110.3728,
        "name": "Kings Peak",
        "regions": [],
        "countries": [
            "United States"
        ],
        "continent": "North America",
        "marker-size": "large",
        "marker-symbol": "triangle",
        "states": [
            "Utah"
        ]
    }
}