{
    "type": "Feature",
    "geometry": {
        "type": "Point",
        "coordinates": [
            -114.1714,
            48.9436
        ]
    },
    "properties": {
        "feet": null,
        "meters": null,
        "latitude": 48.9436,
        "longitude": -114.1714,
        "name": "Kintla Peak",
        "regions": [],
        "countries": [
            "United States"
        ],
        "continent": "North America",
        "marker-size": "large",
        "marker-symbol": "triangle",
        "states": [
            "Montana"
        ]
    }
}