{
    "type": "Feature",
    "geometry": {
        "type": "Point",
        "coordinates": [
            -105.605,
            39.3681
        ]
    },
    "properties": {
        "feet": null,
        "meters": null,
        "latitude": 39.3681,
        "longitude": -105.605,
        "name": "Knobby Crest",
        "regions": [],
        "countries": [
            "United States"
        ],
        "continent": "North America",
        "marker-size": "large",
        "marker-symbol": "triangle",
        "states": [
            "Colorado"
        ]
    }
}