{
    "type": "Feature",
    "geometry": {
        "type": "Point",
        "coordinates": [
            -134.38,
            56.8031
        ]
    },
    "properties": {
        "feet": null,
        "meters": null,
        "latitude": 56.8031,
        "longitude": -134.38,
        "name": "Kuiu Island High Point",
        "regions": [],
        "countries": [
            "United States"
        ],
        "continent": "North America",
        "marker-size": "large",
        "marker-symbol": "triangle",
        "states": [
            "Alaska"
        ]
    }
}