{
    "type": "Feature",
    "geometry": {
        "type": "Point",
        "coordinates": [
            -107.085,
            34.4347
        ]
    },
    "properties": {
        "feet": null,
        "meters": null,
        "latitude": 34.4347,
        "longitude": -107.085,
        "name": "Ladrones Benchmark",
        "regions": [],
        "countries": [
            "United States"
        ],
        "continent": "North America",
        "marker-size": "large",
        "marker-symbol": "triangle",
        "states": [
            "New Mexico"
        ]
    }
}