{
    "type": "Feature",
    "geometry": {
        "type": "Point",
        "coordinates": [
            -121.8442,
            37.1111
        ]
    },
    "properties": {
        "feet": null,
        "meters": null,
        "latitude": 37.1111,
        "longitude": -121.8442,
        "name": "Loma Prieta",
        "regions": [],
        "countries": [
            "United States"
        ],
        "continent": "North America",
        "marker-size": "large",
        "marker-symbol": "triangle",
        "states": [
            "California"
        ]
    }
}