{
    "type": "Feature",
    "geometry": {
        "type": "Point",
        "coordinates": [
            -118.4953,
            44.2889
        ]
    },
    "properties": {
        "feet": null,
        "meters": null,
        "latitude": 44.2889,
        "longitude": -118.4953,
        "name": "Lookout Mountain",
        "regions": [],
        "countries": [
            "United States"
        ],
        "continent": "North America",
        "marker-size": "large",
        "marker-symbol": "triangle",
        "states": [
            "Oregon"
        ]
    }
}