{
    "type": "Feature",
    "geometry": {
        "type": "Point",
        "coordinates": [
            -155.468056,
            19.820667
        ]
    },
    "properties": {
        "feet": 13803.478132,
        "meters": 4207.3,
        "latitude": 19.820667,
        "longitude": -155.468056,
        "name": "Mauna Kea",
        "countries": [
            "United States"
        ],
        "continent": "North America",
        "marker-size": "large",
        "marker-symbol": "triangle"
    }
}