{
    "type": "Feature",
    "geometry": {
        "type": "Point",
        "coordinates": [
            -110.2931,
            31.3928
        ]
    },
    "properties": {
        "feet": null,
        "meters": null,
        "latitude": 31.3928,
        "longitude": -110.2931,
        "name": "Miller Peak",
        "regions": [],
        "countries": [
            "United States"
        ],
        "continent": "North America",
        "marker-size": "large",
        "marker-symbol": "triangle",
        "states": [
            "Arizona"
        ]
    }
}