{
    "type": "Feature",
    "geometry": {
        "type": "Point",
        "coordinates": [
            -119.0614,
            48.3719
        ]
    },
    "properties": {
        "feet": null,
        "meters": null,
        "latitude": 48.3719,
        "longitude": -119.0614,
        "name": "Moses Mountain",
        "regions": [],
        "countries": [
            "United States"
        ],
        "continent": "North America",
        "marker-size": "large",
        "marker-symbol": "triangle",
        "states": [
            "Washington"
        ]
    }
}