{
    "type": "Feature",
    "geometry": {
        "type": "Point",
        "coordinates": [
            -119.1789,
            37.3761
        ]
    },
    "properties": {
        "feet": null,
        "meters": null,
        "latitude": 37.3761,
        "longitude": -119.1789,
        "name": "Mount Tom",
        "regions": [],
        "countries": [
            "United States"
        ],
        "continent": "North America",
        "marker-size": "large",
        "marker-symbol": "triangle",
        "states": [
            "California"
        ]
    }
}