{
    "type": "Feature",
    "geometry": {
        "type": "Point",
        "coordinates": [
            -119.1453,
            34.8128
        ]
    },
    "properties": {
        "feet": null,
        "meters": null,
        "latitude": 34.8128,
        "longitude": -119.1453,
        "name": "Mount Pinos",
        "regions": [],
        "countries": [
            "United States"
        ],
        "continent": "North America",
        "marker-size": "large",
        "marker-symbol": "triangle",
        "states": [
            "California"
        ]
    }
}