{
    "type": "Feature",
    "geometry": {
        "type": "Point",
        "coordinates": [
            -140.9308,
            60.2928
        ]
    },
    "properties": {
        "feet": null,
        "meters": null,
        "latitude": 60.2928,
        "longitude": -140.9308,
        "name": "Mount Saint Elias",
        "regions": [],
        "countries": [
            "United States"
        ],
        "continent": "North America",
        "marker-size": "large",
        "marker-symbol": "triangle",
        "states": [
            "Alaska"
        ]
    }
}