{
    "type": "Feature",
    "geometry": {
        "type": "Point",
        "coordinates": [
            -118.6586,
            37.3386
        ]
    },
    "properties": {
        "feet": null,
        "meters": null,
        "latitude": 37.3386,
        "longitude": -118.6586,
        "name": "Mount Tom",
        "regions": [],
        "countries": [
            "United States"
        ],
        "continent": "North America",
        "marker-size": "large",
        "marker-symbol": "triangle",
        "states": [
            "California"
        ]
    }
}