{
    "type": "Feature",
    "geometry": {
        "type": "Point",
        "coordinates": [
            -139.075,
            60.3517
        ]
    },
    "properties": {
        "feet": null,
        "meters": null,
        "latitude": 60.3517,
        "longitude": -139.075,
        "name": "Mount Alverstone",
        "regions": [],
        "countries": [
            "United States"
        ],
        "continent": "North America",
        "marker-size": "large",
        "marker-symbol": "triangle",
        "states": [
            "Alaska"
        ]
    }
}