{
    "type": "Feature",
    "geometry": {
        "type": "Point",
        "coordinates": [
            -110.5919,
            42.8586
        ]
    },
    "properties": {
        "feet": null,
        "meters": null,
        "latitude": 42.8586,
        "longitude": -110.5919,
        "name": "Mount McDougal",
        "regions": [],
        "countries": [
            "United States"
        ],
        "continent": "North America",
        "marker-size": "large",
        "marker-symbol": "triangle",
        "states": [
            "Wyoming"
        ]
    }
}