{
    "type": "Feature",
    "geometry": {
        "type": "Point",
        "coordinates": [
            -121.2406,
            48.9697
        ]
    },
    "properties": {
        "feet": null,
        "meters": null,
        "latitude": 48.9697,
        "longitude": -121.2406,
        "name": "Mount Spickard",
        "regions": [],
        "countries": [
            "United States"
        ],
        "continent": "North America",
        "marker-size": "large",
        "marker-symbol": "triangle",
        "states": [
            "Washington"
        ]
    }
}