{
    "type": "Feature",
    "geometry": {
        "type": "Point",
        "coordinates": [
            -110.6969,
            37.8875
        ]
    },
    "properties": {
        "feet": null,
        "meters": null,
        "latitude": 37.8875,
        "longitude": -110.6969,
        "name": "Mount Hillers",
        "regions": [],
        "countries": [
            "United States"
        ],
        "continent": "North America",
        "marker-size": "large",
        "marker-symbol": "triangle",
        "states": [
            "Utah"
        ]
    }
}