{
    "type": "Feature",
    "geometry": {
        "type": "Point",
        "coordinates": [
            -109.8078,
            45.275
        ]
    },
    "properties": {
        "feet": null,
        "meters": null,
        "latitude": 45.275,
        "longitude": -109.8078,
        "name": "Mount Wood",
        "regions": [],
        "countries": [
            "United States"
        ],
        "continent": "North America",
        "marker-size": "large",
        "marker-symbol": "triangle",
        "states": [
            "Montana"
        ]
    }
}