{
    "type": "Feature",
    "geometry": {
        "type": "Point",
        "coordinates": [
            -122.4789,
            41.3197
        ]
    },
    "properties": {
        "feet": null,
        "meters": null,
        "latitude": 41.3197,
        "longitude": -122.4789,
        "name": "Mount Eddy",
        "regions": [],
        "countries": [
            "United States"
        ],
        "continent": "North America",
        "marker-size": "large",
        "marker-symbol": "triangle",
        "states": [
            "California"
        ]
    }
}