{
    "type": "Feature",
    "geometry": {
        "type": "Point",
        "coordinates": [
            -110.1394,
            45.3067
        ]
    },
    "properties": {
        "feet": null,
        "meters": null,
        "latitude": 45.3067,
        "longitude": -110.1394,
        "name": "Mount Douglas",
        "regions": [],
        "countries": [
            "United States"
        ],
        "continent": "North America",
        "marker-size": "large",
        "marker-symbol": "triangle",
        "states": [
            "Montana"
        ]
    }
}