{
    "type": "Feature",
    "geometry": {
        "type": "Point",
        "coordinates": [
            -118.8025,
            37.3769
        ]
    },
    "properties": {
        "feet": null,
        "meters": null,
        "latitude": 37.3769,
        "longitude": -118.8025,
        "name": "Mount Gabb",
        "regions": [],
        "countries": [
            "United States"
        ],
        "continent": "North America",
        "marker-size": "large",
        "marker-symbol": "triangle",
        "states": [
            "California"
        ]
    }
}