{
    "type": "Feature",
    "geometry": {
        "type": "Point",
        "coordinates": [
            -121.9142,
            37.8817
        ]
    },
    "properties": {
        "feet": null,
        "meters": null,
        "latitude": 37.8817,
        "longitude": -121.9142,
        "name": "Mount Diablo",
        "regions": [],
        "countries": [
            "United States"
        ],
        "continent": "North America",
        "marker-size": "large",
        "marker-symbol": "triangle",
        "states": [
            "California"
        ]
    }
}