{
    "type": "Feature",
    "geometry": {
        "type": "Point",
        "coordinates": [
            -113.65,
            48.7286
        ]
    },
    "properties": {
        "feet": null,
        "meters": null,
        "latitude": 48.7286,
        "longitude": -113.65,
        "name": "Mount Siyeh",
        "regions": [],
        "countries": [
            "United States"
        ],
        "continent": "North America",
        "marker-size": "large",
        "marker-symbol": "triangle",
        "states": [
            "Montana"
        ]
    }
}