{
    "type": "Feature",
    "geometry": {
        "type": "Point",
        "coordinates": [
            -121.5803,
            47.7744
        ]
    },
    "properties": {
        "feet": null,
        "meters": null,
        "latitude": 47.7744,
        "longitude": -121.5803,
        "name": "Mount Index",
        "regions": [],
        "countries": [
            "United States"
        ],
        "continent": "North America",
        "marker-size": "large",
        "marker-symbol": "triangle",
        "states": [
            "Washington"
        ]
    }
}