{
    "type": "Feature",
    "geometry": {
        "type": "Point",
        "coordinates": [
            -116.0806,
            36.0064
        ]
    },
    "properties": {
        "feet": null,
        "meters": null,
        "latitude": 36.0064,
        "longitude": -116.0806,
        "name": "Nopah Peak",
        "regions": [],
        "countries": [
            "United States"
        ],
        "continent": "North America",
        "marker-size": "large",
        "marker-symbol": "triangle",
        "states": [
            "California"
        ]
    }
}