{
    "type": "Feature",
    "geometry": {
        "type": "Point",
        "coordinates": [
            -117.1325,
            40.675
        ]
    },
    "properties": {
        "feet": null,
        "meters": null,
        "latitude": 40.675,
        "longitude": -117.1325,
        "name": "North Peak",
        "regions": [],
        "countries": [
            "United States"
        ],
        "continent": "North America",
        "marker-size": "large",
        "marker-symbol": "triangle",
        "states": [
            "Nevada"
        ]
    }
}