{
    "type": "Feature",
    "geometry": {
        "type": "Point",
        "coordinates": [
            -118.1183,
            36.2653
        ]
    },
    "properties": {
        "feet": null,
        "meters": null,
        "latitude": 36.2653,
        "longitude": -118.1183,
        "name": "Olancha Peak",
        "regions": [],
        "countries": [
            "United States"
        ],
        "continent": "North America",
        "marker-size": "large",
        "marker-symbol": "triangle",
        "states": [
            "California"
        ]
    }
}