{
    "type": "Feature",
    "geometry": {
        "type": "Point",
        "coordinates": [
            -123.8464,
            42.2986
        ]
    },
    "properties": {
        "feet": null,
        "meters": null,
        "latitude": 42.2986,
        "longitude": -123.8464,
        "name": "Pearsoll Peak",
        "regions": [],
        "countries": [
            "United States"
        ],
        "continent": "North America",
        "marker-size": "large",
        "marker-symbol": "triangle",
        "states": [
            "Oregon"
        ]
    }
}