{
    "type": "Feature",
    "geometry": {
        "type": "Point",
        "coordinates": [
            -108.7719,
            38.8261
        ]
    },
    "properties": {
        "feet": null,
        "meters": null,
        "latitude": 38.8261,
        "longitude": -108.7719,
        "name": "Pi\u00f1on Mesa HP",
        "regions": [],
        "countries": [
            "United States"
        ],
        "continent": "North America",
        "marker-size": "large",
        "marker-symbol": "triangle",
        "states": [
            "Colorado"
        ]
    }
}