{
    "type": "Feature",
    "geometry": {
        "type": "Point",
        "coordinates": [
            -172.5106,
            52.3158
        ]
    },
    "properties": {
        "feet": null,
        "meters": null,
        "latitude": 52.3158,
        "longitude": -172.5106,
        "name": "Pyre Peak",
        "regions": [],
        "countries": [
            "United States"
        ],
        "continent": "North America",
        "marker-size": "large",
        "marker-symbol": "triangle",
        "states": [
            "Alaska"
        ]
    }
}