{
    "type": "Feature",
    "geometry": {
        "type": "Point",
        "coordinates": [
            -120.1967,
            48.9233
        ]
    },
    "properties": {
        "feet": null,
        "meters": null,
        "latitude": 48.9233,
        "longitude": -120.1967,
        "name": "Remmel Mountain",
        "regions": [],
        "countries": [
            "United States"
        ],
        "continent": "North America",
        "marker-size": "large",
        "marker-symbol": "triangle",
        "states": [
            "Washington"
        ]
    }
}