{
    "type": "Feature",
    "geometry": {
        "type": "Point",
        "coordinates": [
            -107.3925,
            37.6797
        ]
    },
    "properties": {
        "feet": null,
        "meters": null,
        "latitude": 37.6797,
        "longitude": -107.3925,
        "name": "Rio Grande Pyramid",
        "regions": [],
        "countries": [
            "United States"
        ],
        "continent": "North America",
        "marker-size": "large",
        "marker-symbol": "triangle",
        "states": [
            "Colorado"
        ]
    }
}