{
    "type": "Feature",
    "geometry": {
        "type": "Point",
        "coordinates": [
            -115.4753,
            40.6217
        ]
    },
    "properties": {
        "feet": null,
        "meters": null,
        "latitude": 40.6217,
        "longitude": -115.4753,
        "name": "Ruby Dome",
        "regions": [],
        "countries": [
            "United States"
        ],
        "continent": "North America",
        "marker-size": "large",
        "marker-symbol": "triangle",
        "states": [
            "Nevada"
        ]
    }
}