{
    "type": "Feature",
    "geometry": {
        "type": "Point",
        "coordinates": [
            -121.0428,
            48.6944
        ]
    },
    "properties": {
        "feet": null,
        "meters": null,
        "latitude": 48.6944,
        "longitude": -121.0428,
        "name": "Ruby Mountain",
        "regions": [],
        "countries": [
            "United States"
        ],
        "continent": "North America",
        "marker-size": "large",
        "marker-symbol": "triangle",
        "states": [
            "Washington"
        ]
    }
}