{
    "type": "Feature",
    "geometry": {
        "type": "Point",
        "coordinates": [
            -117.2928,
            45.245
        ]
    },
    "properties": {
        "feet": null,
        "meters": null,
        "latitude": 45.245,
        "longitude": -117.2928,
        "name": "Sacajawea Peak",
        "regions": [],
        "countries": [
            "United States"
        ],
        "continent": "North America",
        "marker-size": "large",
        "marker-symbol": "triangle",
        "states": [
            "Oregon"
        ]
    }
}