{
    "type": "Feature",
    "geometry": {
        "type": "Point",
        "coordinates": [
            -106.0186,
            36.8594
        ]
    },
    "properties": {
        "feet": null,
        "meters": null,
        "latitude": 36.8594,
        "longitude": -106.0186,
        "name": "San Antonio Mountain",
        "regions": [],
        "countries": [
            "United States"
        ],
        "continent": "North America",
        "marker-size": "large",
        "marker-symbol": "triangle",
        "states": [
            "New Mexico"
        ]
    }
}