{
    "type": "Feature",
    "geometry": {
        "type": "Point",
        "coordinates": [
            -119.1061,
            37.7189
        ]
    },
    "properties": {
        "feet": null,
        "meters": null,
        "latitude": 37.7189,
        "longitude": -119.1061,
        "name": "San Joaquin Mountain",
        "regions": [],
        "countries": [
            "United States"
        ],
        "continent": "North America",
        "marker-size": "large",
        "marker-symbol": "triangle",
        "states": [
            "California"
        ]
    }
}