{
    "type": "Feature",
    "geometry": {
        "type": "Point",
        "coordinates": [
            -80.8539,
            37.2475
        ]
    },
    "properties": {
        "feet": null,
        "meters": null,
        "latitude": 37.2475,
        "longitude": -80.8539,
        "name": "Sugar Run Mountain",
        "regions": [],
        "countries": [
            "United States"
        ],
        "continent": "North America",
        "marker-size": "large",
        "marker-symbol": "triangle",
        "states": [
            "Virginia"
        ]
    }
}