{
    "type": "Feature",
    "geometry": {
        "type": "Point",
        "coordinates": [
            -178.1428,
            51.8839
        ]
    },
    "properties": {
        "feet": null,
        "meters": null,
        "latitude": 51.8839,
        "longitude": -178.1428,
        "name": "Tanaga Volcano",
        "regions": [],
        "countries": [
            "United States"
        ],
        "continent": "North America",
        "marker-size": "large",
        "marker-symbol": "triangle",
        "states": [
            "Alaska"
        ]
    }
}