{
    "type": "Feature",
    "geometry": {
        "type": "Point",
        "coordinates": [
            -117.2517,
            38.7989
        ]
    },
    "properties": {
        "feet": null,
        "meters": null,
        "latitude": 38.7989,
        "longitude": -117.2517,
        "name": "Toiyabe Dome",
        "regions": [],
        "countries": [
            "United States"
        ],
        "continent": "North America",
        "marker-size": "large",
        "marker-symbol": "triangle",
        "states": [
            "Nevada"
        ]
    }
}