{
    "type": "Feature",
    "geometry": {
        "type": "Point",
        "coordinates": [
            -119.5478,
            38.1444
        ]
    },
    "properties": {
        "feet": null,
        "meters": null,
        "latitude": 38.1444,
        "longitude": -119.5478,
        "name": "Tower Peak",
        "regions": [],
        "countries": [
            "United States"
        ],
        "continent": "North America",
        "marker-size": "large",
        "marker-symbol": "triangle",
        "states": [
            "California"
        ]
    }
}