{
    "type": "Feature",
    "geometry": {
        "type": "Point",
        "coordinates": [
            -110.1517,
            44.0964
        ]
    },
    "properties": {
        "feet": null,
        "meters": null,
        "latitude": 44.0964,
        "longitude": -110.1517,
        "name": "Two Ocean Mountain",
        "regions": [],
        "countries": [
            "United States"
        ],
        "continent": "North America",
        "marker-size": "large",
        "marker-symbol": "triangle",
        "states": [
            "Wyoming"
        ]
    }
}