{
    "type": "Feature",
    "geometry": {
        "type": "Point",
        "coordinates": [
            -113.5839,
            38.3603
        ]
    },
    "properties": {
        "feet": null,
        "meters": null,
        "latitude": 38.3603,
        "longitude": -113.5839,
        "name": "Wah Wah Mountain",
        "regions": [],
        "countries": [
            "United States"
        ],
        "continent": "North America",
        "marker-size": "large",
        "marker-symbol": "triangle",
        "states": [
            "Utah"
        ]
    }
}