{
    "type": "Feature",
    "geometry": {
        "type": "Point",
        "coordinates": [
            -106.125,
            38.9917
        ]
    },
    "properties": {
        "feet": null,
        "meters": null,
        "latitude": 38.9917,
        "longitude": -106.125,
        "name": "West Buffalo Peak",
        "regions": [],
        "countries": [
            "United States"
        ],
        "continent": "North America",
        "marker-size": "large",
        "marker-symbol": "triangle",
        "states": [
            "Colorado"
        ]
    }
}