{
    "type": "Feature",
    "geometry": {
        "type": "Point",
        "coordinates": [
            -113.8833,
            37.1553
        ]
    },
    "properties": {
        "feet": null,
        "meters": null,
        "latitude": 37.1553,
        "longitude": -113.8833,
        "name": "West Mountain Peak",
        "regions": [],
        "countries": [
            "United States"
        ],
        "continent": "North America",
        "marker-size": "large",
        "marker-symbol": "triangle",
        "states": [
            "Utah"
        ]
    }
}