{
    "type": "Feature",
    "geometry": {
        "type": "Point",
        "coordinates": [
            -106.98,
            38.8222
        ]
    },
    "properties": {
        "feet": null,
        "meters": null,
        "latitude": 38.8222,
        "longitude": -106.98,
        "name": "Whetstone Mountain",
        "regions": [],
        "countries": [
            "United States"
        ],
        "continent": "North America",
        "marker-size": "large",
        "marker-symbol": "triangle",
        "states": [
            "Colorado"
        ]
    }
}