{
    "type": "Feature",
    "geometry": {
        "type": "Point",
        "coordinates": [
            -121.4169,
            48.2086
        ]
    },
    "properties": {
        "feet": null,
        "meters": null,
        "latitude": 48.2086,
        "longitude": -121.4169,
        "name": "White Chuck Mountain(Hi Khaed)",
        "regions": [],
        "countries": [
            "United States"
        ],
        "continent": "North America",
        "marker-size": "large",
        "marker-symbol": "triangle",
        "states": [
            "Washington"
        ]
    }
}