{
  "type": "Feature",
  "geometry": {
    "type": "Point",
    "coordinates": [
      9.571389,
      47.175
    ]
  },
  "properties": {
    "feet": 6736,
    "meters": 2053,
    "latitude": 47.175,
    "longitude": 9.571389,
    "name": "Drei Schwestern",
    "regions": [
      "Northern Alps",
      "Saint Gallen Alps"
    ],
    "countries": [
      "Liechtenstein"
    ],
    "continent": "Europe",
    "marker-size": "medium",
    "marker-symbol": "triangle"
  }
}
