{
    "type": "Feature",
    "geometry": {
        "type": "Point",
        "coordinates": [
            -110.37277777777777,
            40.77638888888889
        ]
    },
    "properties": {
        "feet": null,
        "meters": null,
        "latitude": 40.77638888888889,
        "longitude": -110.37277777777777,
        "name": "Kings Peak",
        "regions": [],
        "countries": [
            "United States"
        ],
        "continent": "North America",
        "marker-size": "large",
        "marker-symbol": "triangle",
        "state": "Utah"
    }
}