{
  "type": "Feature",
  "geometry": {
    "type": "Point",
    "coordinates": [
      -110.367,
      40.7833
    ]
  },
  "properties": {
    "feet": 13528,
    "meters": 4123,
    "latitude": 40.7833,
    "longitude": -110.367,
    "name": "Kings Peak",
    "regions": [
      "Rocky Mountains",
      "Uinta Range"
    ],
    "states": [
      "Utah"
    ],
    "countries": [
      "United States"
    ],
    "continent": "North America",
    "marker-size": "medium",
    "marker-symbol": "triangle"
  }
}
