{
  "type": "Feature",
  "geometry": {
    "type": "Point",
    "coordinates": [
      -6.321879,
      42.801438
    ]
  },
  "properties": {
    "feet": 6946,
    "meters": 2117,
    "latitude": 42.801438,
    "longitude": -6.321879,
    "name": "Catoute",
    "regions": [
      "Iberian Peninsula",
      "Cordillera Cantabrica"
    ],
    "countries": [
      "Spain"
    ],
    "continent": "Europe",
    "marker-size": "medium",
    "marker-symbol": "triangle"
  }
}
