{
  "type": "Feature",
  "geometry": {
    "type": "Point",
    "coordinates": [
      2.180185,
      42.418451
    ]
  },
  "properties": {
    "feet": 8894,
    "meters": 2711,
    "latitude": 42.418451,
    "longitude": 2.180185,
    "name": "Torreneules",
    "regions": [
      "Iberian Peninsula",
      "Pyrenees"
    ],
    "countries": [
      "Spain"
    ],
    "continent": "Europe",
    "marker-size": "medium",
    "marker-symbol": "triangle"
  }
}
