{
    "type": "Feature",
    "geometry": {
        "type": "Point",
        "coordinates": [
            -156.84972222222223,
            21.1325
        ]
    },
    "properties": {
        "feet": null,
        "meters": null,
        "latitude": 21.1325,
        "longitude": -156.84972222222223,
        "name": "Oloku\u02bbi",
        "regions": [],
        "countries": [
            "United States"
        ],
        "continent": "australia-oceania",
        "marker-size": "large",
        "marker-symbol": "triangle",
        "state": "Hawaii"
    }
}