{
  "type": "Feature",
  "geometry": {
    "type": "Point",
    "coordinates": [
      -66.272665,
      -17.239812
    ]
  },
  "properties": {
    "feet": 14974,
    "meters": 4564,
    "latitude": -17.239812,
    "longitude": -66.272665,
    "name": "Cerro Santiago",
    "regions": [
      "Andes",
      "Bolivian Andes"
    ],
    "countries": [
      "Bolivia"
    ],
    "continent": "South America",
    "marker-size": "large",
    "marker-symbol": "triangle"
  }
}
