{
  "type": "Feature",
  "geometry": {
    "type": "Point",
    "coordinates": [
      -81.8944,
      35.8383
    ]
  },
  "properties": {
    "feet": 2920,
    "meters": 890,
    "latitude": 35.8383,
    "longitude": -81.8944,
    "name": "Shortoff Mountain",
    "regions": [
      "Appalachian Mountains"
    ],
    "states": [
      "North Carolina"
    ],
    "countries": [
      "United States"
    ],
    "continent": "North America",
    "marker-size": "medium",
    "marker-symbol": "triangle"
  }
}
