{
    "type": "Feature",
    "geometry": {
        "type": "Point",
        "coordinates": [
            -155.4681,
            19.8208
        ]
    },
    "properties": {
        "feet": null,
        "meters": null,
        "latitude": 19.8208,
        "longitude": -155.4681,
        "name": "Mauna Kea",
        "regions": [],
        "countries": [
            "United States"
        ],
        "continent": "australia-oceania",
        "marker-size": "large",
        "marker-symbol": "triangle",
        "states": [
            "Hawaii"
        ]
    }
}