{
  "type": "Feature",
  "geometry": {
    "type": "Point",
    "coordinates": [
      81.3167,
      31.0667
    ]
  },
  "properties": {
    "feet": 22028,
    "meters": 6714,
    "latitude": 31.0667,
    "longitude": 81.3167,
    "name": "Kailas",
    "regions": [
      "Gangdisi Shanmai"
    ],
    "countries": [
      "China"
    ],
    "continent": "Asia",
    "marker-size": "large",
    "marker-symbol": "triangle"
  }
}
