{
  "type": "FeatureCollection",
  "features": [
    {
      "type": "Feature",
      "geometry": {
        "type": "Point",
        "coordinates": [
          25.634444,
          54.529444
        ]
      },
      "properties": {
        "feet": 961,
        "meters": 293,
        "latitude": 54.529444,
        "longitude": 25.634444,
        "name": "Aukstojas",
        "countries": [
          "Lithuania"
        ],
        "continent": "Europe",
        "marker-size": "small",
        "marker-symbol": "triangle"
      }
    },
    {
      "type": "Feature",
      "geometry": {
        "type": "Point",
        "coordinates": [
          25.5667,
          54.4667
        ]
      },
      "properties": {
        "feet": 963,
        "meters": 294,
        "latitude": 54.4667,
        "longitude": 25.5667,
        "name": "Juozapine",
        "countries": [
          "Lithuania"
        ],
        "continent": "Europe",
        "marker-size": "small",
        "marker-symbol": "triangle"
      }
    }
  ]
}
