{
  "type": "Feature",
  "geometry": {
    "type": "Point",
    "coordinates": [
      -123.551217,
      44.504287
    ]
  },
  "properties": {
    "feet": 4097,
    "meters": 1249,
    "latitude": 44.504287,
    "longitude": -123.551217,
    "name": "Marys Peak",
    "regions": [
      "Pacific Ranges",
      "Northwest U.S. Coast Ranges"
    ],
    "states": [
      "Oregon"
    ],
    "countries": [
      "United States"
    ],
    "continent": "North America",
    "marker-size": "medium",
    "marker-symbol": "triangle"
  }
}
