{
  "type": "Feature",
  "geometry": {
    "type": "Point",
    "coordinates": [
      -123.456501,
      45.371499
    ]
  },
  "properties": {
    "feet": 3412,
    "meters": 1040,
    "latitude": 45.371499,
    "longitude": -123.456501,
    "name": "Trask Mountain",
    "regions": [
      "Pacific Ranges",
      "Northwest U.S. Coast Ranges"
    ],
    "states": [
      "Oregon"
    ],
    "countries": [
      "United States"
    ],
    "continent": "North America",
    "marker-size": "medium",
    "marker-symbol": "triangle"
  }
}
