{
    "type": "Feature",
    "geometry": {
        "type": "Point",
        "coordinates": [
            -121.11388888888888,
            48.112500000000004
        ]
    },
    "properties": {
        "feet": null,
        "meters": null,
        "latitude": 48.112500000000004,
        "longitude": -121.11388888888888,
        "name": "Glacier Peak",
        "regions": [],
        "countries": [
            "United States"
        ],
        "continent": "North America",
        "marker-size": "large",
        "marker-symbol": "triangle",
        "state": "Washington"
    }
}