{
  "type": "Feature",
  "geometry": {
    "type": "Point",
    "coordinates": [
      -120.656,
      48.5374
    ]
  },
  "properties": {
    "feet": 7560,
    "meters": 2304,
    "latitude": 48.5374,
    "longitude": -120.656,
    "name": "Hinkhouse Peak",
    "regions": [
      "Pacific Ranges",
      "Cascade Range"
    ],
    "states": [
      "Washington"
    ],
    "countries": [
      "United States"
    ],
    "continent": "North America",
    "marker-size": "medium",
    "marker-symbol": "triangle"
  }
}
