{
  "type": "Feature",
  "geometry": {
    "type": "Point",
    "coordinates": [
      -121.478062,
      47.462509
    ]
  },
  "properties": {
    "feet": 6259,
    "meters": 1908,
    "latitude": 47.462509,
    "longitude": -121.478062,
    "name": "Kaleetan Peak",
    "regions": [
      "Pacific Ranges",
      "Cascade Range"
    ],
    "states": [
      "Washington"
    ],
    "countries": [
      "United States"
    ],
    "continent": "North America",
    "marker-size": "medium",
    "marker-symbol": "triangle"
  }
}
