{
  "type": "Feature",
  "geometry": {
    "type": "Point",
    "coordinates": [
      -123.059492,
      47.867509
    ]
  },
  "properties": {
    "feet": 6280,
    "meters": 1914,
    "latitude": 47.867509,
    "longitude": -123.059492,
    "name": "Mount Townsend",
    "regions": [
      "Pacific Ranges",
      "Olympic Mountains"
    ],
    "states": [
      "Washington"
    ],
    "countries": [
      "United States"
    ],
    "continent": "North America",
    "marker-size": "medium",
    "marker-symbol": "triangle"
  }
}
