{
  "type": "Feature",
  "geometry": {
    "type": "Point",
    "coordinates": [
      -121.482482,
      48.754123
    ]
  },
  "properties": {
    "feet": 7680,
    "meters": 2341,
    "latitude": 48.754123,
    "longitude": -121.482482,
    "name": "Mount Blum",
    "regions": [
      "Pacific Ranges",
      "Cascade Range"
    ],
    "states": [
      "Washington"
    ],
    "countries": [
      "United States"
    ],
    "continent": "North America",
    "marker-size": "medium",
    "marker-symbol": "triangle"
  }
}
