{
  "type": "Feature",
  "geometry": {
    "type": "Point",
    "coordinates": [
      -123.256087,
      47.551912
    ]
  },
  "properties": {
    "feet": 6154,
    "meters": 1876,
    "latitude": 47.551912,
    "longitude": -123.256087,
    "name": "Mount Pershing",
    "regions": [
      "Pacific Ranges",
      "Olympic Mountains"
    ],
    "states": [
      "Washington"
    ],
    "countries": [
      "United States"
    ],
    "continent": "North America",
    "marker-size": "medium",
    "marker-symbol": "triangle"
  }
}
