{
    "type": "Feature",
    "geometry": {
        "type": "Point",
        "coordinates": [
            -123.71083333333334,
            47.80138888888889
        ]
    },
    "properties": {
        "feet": null,
        "meters": null,
        "latitude": 47.80138888888889,
        "longitude": -123.71083333333334,
        "name": "Mount Olympus",
        "regions": [],
        "countries": [
            "United States"
        ],
        "continent": "North America",
        "marker-size": "large",
        "marker-symbol": "triangle",
        "state": "Washington"
    }
}