{
  "type": "Feature",
  "geometry": {
    "type": "Point",
    "coordinates": [
      -121.750832,
      48.326468
    ]
  },
  "properties": {
    "feet": 5320,
    "meters": 1622,
    "latitude": 48.326468,
    "longitude": -121.750832,
    "name": "Round Mountain",
    "regions": [
      "Pacific Ranges",
      "Cascade Range"
    ],
    "states": [
      "Washington"
    ],
    "countries": [
      "United States"
    ],
    "continent": "North America",
    "marker-size": "medium",
    "marker-symbol": "triangle"
  }
}
