{
  "type": "Feature",
  "geometry": {
    "type": "Point",
    "coordinates": [
      -121.589427,
      47.495545
    ]
  },
  "properties": {
    "feet": 5123,
    "meters": 1561,
    "latitude": 47.495545,
    "longitude": -121.589427,
    "name": "Russian Butte",
    "regions": [
      "Pacific Ranges",
      "Cascade Range"
    ],
    "states": [
      "Washington"
    ],
    "countries": [
      "United States"
    ],
    "continent": "North America",
    "marker-size": "medium",
    "marker-symbol": "triangle"
  }
}
