{
  "type": "Feature",
  "geometry": {
    "type": "Point",
    "coordinates": [
      -123.237333,
      47.832431
    ]
  },
  "properties": {
    "feet": 7580,
    "meters": 2310,
    "latitude": 47.832431,
    "longitude": -123.237333,
    "name": "Sweat Spire",
    "regions": [
      "Pacific Ranges",
      "Olympic Mountains"
    ],
    "states": [
      "Washington"
    ],
    "countries": [
      "United States"
    ],
    "continent": "North America",
    "marker-size": "medium",
    "marker-symbol": "triangle"
  }
}
