{
  "type": "Feature",
  "geometry": {
    "type": "Point",
    "coordinates": [
      -121.01788,
      48.431735
    ]
  },
  "properties": {
    "feet": 7530,
    "meters": 2295,
    "latitude": 48.431735,
    "longitude": -121.01788,
    "name": "Trapper Mountain",
    "regions": [
      "Pacific Ranges",
      "Cascade Range"
    ],
    "states": [
      "Washington"
    ],
    "countries": [
      "United States"
    ],
    "continent": "North America",
    "marker-size": "medium",
    "marker-symbol": "triangle"
  }
}
