{
  "type": "Feature",
  "geometry": {
    "type": "Point",
    "coordinates": [
      174.764167,
      -36.879722
    ]
  },
  "properties": {
    "feet": 643,
    "meters": 196,
    "latitude": -36.879722,
    "longitude": 174.764167,
    "name": "Mount Eden",
    "regions": [
      "New Zealand",
      "North Island"
    ],
    "countries": [
      "New Zealand"
    ],
    "continent": "Australia/Oceania",
    "marker-size": "small",
    "marker-symbol": "triangle"
  }
}
