{
  "type": "Feature",
  "geometry": {
    "type": "Point",
    "coordinates": [
      -71.56477,
      -39.863701
    ]
  },
  "properties": {
    "feet": 5249,
    "meters": 1600,
    "latitude": -39.863701,
    "longitude": -71.56477,
    "name": "Achen Niyeu",
    "regions": [
      "Andes",
      "Patagonia"
    ],
    "countries": [
      "Argentina"
    ],
    "continent": "South America",
    "marker-size": "medium",
    "marker-symbol": "triangle"
  }
}
