{
  "type": "Feature",
  "geometry": {
    "type": "Point",
    "coordinates": [
      14.465,
      -90.743056
    ]
  },
  "properties": {
    "feet": 11174,
    "meters": 3406,
    "latitude": -90.743056,
    "longitude": 14.465,
    "name": "Volcan Antigua",
    "countries": [
      "Antigua and Barbuda"
    ],
    "continent": "North America",
    "marker-size": "medium",
    "marker-symbol": "triangle"
  }
}
