{
  "type": "Feature",
  "geometry": {
    "type": "Point",
    "coordinates": [
      -119.117,
      37.75
    ]
  },
  "properties": {
    "feet": 10909,
    "meters": 3325,
    "latitude": 37.75,
    "longitude": -119.117,
    "name": "Carson Peak",
    "regions": [
      "Pacific Ranges",
      "Sierra Nevada"
    ],
    "states": [
      "California"
    ],
    "countries": [
      "United States"
    ],
    "continent": "North America",
    "marker-size": "medium",
    "marker-symbol": "triangle"
  }
}
