{
    "type": "Feature",
    "geometry": {
        "type": "Point",
        "coordinates": [
            -119.78444444444445,
            34.02916666666667
        ]
    },
    "properties": {
        "feet": null,
        "meters": null,
        "latitude": 34.02916666666667,
        "longitude": -119.78444444444445,
        "name": "Devils Peak",
        "regions": [],
        "countries": [
            "United States"
        ],
        "continent": "North America",
        "marker-size": "large",
        "marker-symbol": "triangle",
        "state": "California"
    }
}