{
    "type": "Feature",
    "geometry": {
        "type": "Point",
        "coordinates": [
            -116.62388888888889,
            36.10333333333333
        ]
    },
    "properties": {
        "feet": null,
        "meters": null,
        "latitude": 36.10333333333333,
        "longitude": -116.62388888888889,
        "name": "Funeral Peak",
        "regions": [],
        "countries": [
            "United States"
        ],
        "continent": "North America",
        "marker-size": "large",
        "marker-symbol": "triangle",
        "state": "California"
    }
}