{
    "type": "Feature",
    "geometry": {
        "type": "Point",
        "coordinates": [
            -118.65861111111111,
            37.33861111111111
        ]
    },
    "properties": {
        "feet": null,
        "meters": null,
        "latitude": 37.33861111111111,
        "longitude": -118.65861111111111,
        "name": "Mount Tom",
        "regions": [],
        "countries": [
            "United States"
        ],
        "continent": "North America",
        "marker-size": "large",
        "marker-symbol": "triangle",
        "state": "California"
    }
}