{
  "type": "Feature",
  "geometry": {
    "type": "Point",
    "coordinates": [
      -118.658,
      37.3386
    ]
  },
  "properties": {
    "feet": 13652,
    "meters": 4161,
    "latitude": 37.3386,
    "longitude": -118.658,
    "name": "Mount Tom",
    "regions": [
      "Pacific Ranges",
      "Sierra Nevada"
    ],
    "states": [
      "California"
    ],
    "countries": [
      "United States"
    ],
    "continent": "North America",
    "marker-size": "medium",
    "marker-symbol": "triangle"
  }
}
