{
  "type": "Feature",
  "geometry": {
    "type": "Point",
    "coordinates": [
      -118.661,
      37.1503
    ]
  },
  "properties": {
    "feet": 13435,
    "meters": 4095,
    "latitude": 37.1503,
    "longitude": -118.661,
    "name": "Mount Haeckel",
    "regions": [
      "Pacific Ranges",
      "Sierra Nevada"
    ],
    "states": [
      "California"
    ],
    "countries": [
      "United States"
    ],
    "continent": "North America",
    "marker-size": "medium",
    "marker-symbol": "triangle"
  }
}
