{
    "type": "Feature",
    "geometry": {
        "type": "Point",
        "coordinates": [
            -117.6463888888889,
            34.28916666666667
        ]
    },
    "properties": {
        "feet": null,
        "meters": null,
        "latitude": 34.28916666666667,
        "longitude": -117.6463888888889,
        "name": "Mount San Antonio",
        "regions": [],
        "countries": [
            "United States"
        ],
        "continent": "North America",
        "marker-size": "large",
        "marker-symbol": "triangle",
        "state": "California"
    }
}