{
    "type": "Feature",
    "geometry": {
        "type": "Point",
        "coordinates": [
            -121.91416666666667,
            37.88166666666667
        ]
    },
    "properties": {
        "feet": null,
        "meters": null,
        "latitude": 37.88166666666667,
        "longitude": -121.91416666666667,
        "name": "Mount Diablo",
        "regions": [],
        "countries": [
            "United States"
        ],
        "continent": "North America",
        "marker-size": "large",
        "marker-symbol": "triangle",
        "state": "California"
    }
}