{
    "type": "Feature",
    "geometry": {
        "type": "Point",
        "coordinates": [
            -118.67222222222223,
            37.16694444444444
        ]
    },
    "properties": {
        "feet": null,
        "meters": null,
        "latitude": 37.16694444444444,
        "longitude": -118.67222222222223,
        "name": "Mount Darwin",
        "regions": [],
        "countries": [
            "United States"
        ],
        "continent": "North America",
        "marker-size": "large",
        "marker-symbol": "triangle",
        "state": "California"
    }
}