{
    "type": "Feature",
    "geometry": {
        "type": "Point",
        "coordinates": [
            -118.40527777777778,
            36.947222222222216
        ]
    },
    "properties": {
        "feet": null,
        "meters": null,
        "latitude": 36.947222222222216,
        "longitude": -118.40527777777778,
        "name": "Mount Pinchot",
        "regions": [],
        "countries": [
            "United States"
        ],
        "continent": "North America",
        "marker-size": "large",
        "marker-symbol": "triangle",
        "state": "California"
    }
}