{
  "type": "Feature",
  "geometry": {
    "type": "Point",
    "coordinates": [
      -118.671,
      37.1669
    ]
  },
  "properties": {
    "feet": 13831,
    "meters": 4216,
    "latitude": 37.1669,
    "longitude": -118.671,
    "name": "Mount Darwin",
    "regions": [
      "Pacific Ranges",
      "Sierra Nevada"
    ],
    "states": [
      "California"
    ],
    "countries": [
      "United States"
    ],
    "continent": "North America",
    "marker-size": "large",
    "marker-symbol": "triangle"
  }
}
