{
  "type": "Feature",
  "geometry": {
    "type": "Point",
    "coordinates": [
      -119.314,
      37.9822
    ]
  },
  "properties": {
    "feet": 12242,
    "meters": 3731,
    "latitude": 37.9822,
    "longitude": -119.314,
    "name": "North Peak",
    "regions": [
      "Pacific Ranges",
      "Sierra Nevada"
    ],
    "states": [
      "California"
    ],
    "countries": [
      "United States"
    ],
    "continent": "North America",
    "marker-size": "medium",
    "marker-symbol": "triangle"
  }
}
