{
    "type": "Feature",
    "geometry": {
        "type": "Point",
        "coordinates": [
            -118.11833333333333,
            36.265277777777776
        ]
    },
    "properties": {
        "feet": null,
        "meters": null,
        "latitude": 36.265277777777776,
        "longitude": -118.11833333333333,
        "name": "Olancha Peak",
        "regions": [],
        "countries": [
            "United States"
        ],
        "continent": "North America",
        "marker-size": "large",
        "marker-symbol": "triangle",
        "state": "California"
    }
}