{
    "type": "Feature",
    "geometry": {
        "type": "Point",
        "coordinates": [
            -118.11815035,
            36.265179578
        ]
    },
    "properties": {
        "feet": 12132.0,
        "meters": 3697.8334816693286,
        "latitude": 36.265179578,
        "longitude": -118.11815035,
        "name": "Olancha Peak",
        "countries": [
            "United States"
        ],
        "continent": "North America",
        "marker-size": "large",
        "marker-symbol": "triangle",
        "states": [
            "California"
        ]
    }
}