{
    "type": "Feature",
    "geometry": {
        "type": "Point",
        "coordinates": [
            -116.815,
            34.675
        ]
    },
    "properties": {
        "feet": null,
        "meters": null,
        "latitude": 34.675,
        "longitude": -116.815,
        "name": "Ord Mountain",
        "regions": [],
        "countries": [
            "United States"
        ],
        "continent": "North America",
        "marker-size": "large",
        "marker-symbol": "triangle",
        "state": "California"
    }
}