{
  "type": "Feature",
  "geometry": {
    "type": "Point",
    "coordinates": [
      -68.80012,
      10.404248
    ]
  },
  "properties": {
    "feet": 6381,
    "meters": 1945,
    "latitude": 10.404248,
    "longitude": -68.80012,
    "name": "Cerro Tigre",
    "regions": [
      "Coastal South America",
      "Coastal Venezuela"
    ],
    "countries": [
      "Venezuela"
    ],
    "continent": "South America",
    "marker-size": "medium",
    "marker-symbol": "triangle"
  }
}
