{
  "type": "Feature",
  "geometry": {
    "type": "Point",
    "coordinates": [
      -66.394672,
      9.974472
    ]
  },
  "properties": {
    "feet": 4134,
    "meters": 1260,
    "latitude": 9.974472,
    "longitude": -66.394672,
    "name": "Cerro Santa Inés",
    "regions": [
      "Coastal South America",
      "Coastal Venezuela"
    ],
    "countries": [
      "Venezuela"
    ],
    "continent": "South America",
    "marker-size": "medium",
    "marker-symbol": "triangle"
  }
}
