{
  "type": "Feature",
  "geometry": {
    "type": "Point",
    "coordinates": [
      -67.937737,
      10.3625
    ]
  },
  "properties": {
    "feet": 6542,
    "meters": 2004,
    "latitude": 10.3625,
    "longitude": -67.937737,
    "name": "Pico Caobal",
    "regions": [
      "Coastal South America",
      "Coastal Venezuela"
    ],
    "countries": [
      "Venezuela"
    ],
    "continent": "South America",
    "marker-size": "medium",
    "marker-symbol": "triangle"
  }
}
