{
  "type": "Feature",
  "geometry": {
    "type": "Point",
    "coordinates": [
      152.614396,
      -28.269393
    ]
  },
  "properties": {
    "feet": 4308,
    "meters": 1313,
    "latitude": -28.269393,
    "longitude": 152.614396,
    "name": "Mt Ballow",
    "regions": [
      "Great Dividing Range",
      "South Queensland Great Dividing Range"
    ],
    "countries": [
      "Australia"
    ],
    "continent": "Australia/Oceania",
    "marker-size": "medium",
    "marker-symbol": "triangle"
  }
}
