{
    "type": "Feature",
    "geometry": {
        "type": "Point",
        "coordinates": [
            -90.8756,
            14.5017
        ]
    },
    "properties": {
        "feet": null,
        "meters": null,
        "latitude": 14.5017,
        "longitude": -90.8756,
        "name": "Volc\u00e1n Acatenango",
        "regions": [],
        "countries": [
            "Guatemala"
        ],
        "continent": "North America",
        "marker-size": "large",
        "marker-symbol": "triangle"
    }
}