{
    "type": "Feature",
    "geometry": {
        "type": "Point",
        "coordinates": [
            -111.5756642,
            31.7914724
        ]
    },
    "properties": {
        "feet": null,
        "meters": null,
        "latitude": 31.7914724,
        "longitude": -111.5756642,
        "name": "Baboquivari Peak",
        "countries": [
            "United States"
        ],
        "continent": "North America",
        "marker-size": null,
        "marker-symbol": "triangle",
        "states": [
            "Arizona"
        ]
    }
}