{
    "type": "Feature",
    "geometry": {
        "type": "Point",
        "coordinates": [
            -111.59583333333333,
            31.77111111111111
        ]
    },
    "properties": {
        "feet": null,
        "meters": null,
        "latitude": 31.77111111111111,
        "longitude": -111.59583333333333,
        "name": "Baboquivari Peak",
        "regions": [],
        "countries": [
            "United States"
        ],
        "continent": "North America",
        "marker-size": "large",
        "marker-symbol": "triangle",
        "state": "Arizona"
    }
}