{
    "type": "Feature",
    "geometry": {
        "type": "Point",
        "coordinates": [
            -112.40444444444445,
            34.415
        ]
    },
    "properties": {
        "feet": null,
        "meters": null,
        "latitude": 34.415,
        "longitude": -112.40444444444445,
        "name": "Mount Union",
        "regions": [],
        "countries": [
            "United States"
        ],
        "continent": "North America",
        "marker-size": "large",
        "marker-symbol": "triangle",
        "state": "Arizona"
    }
}