{
    "type": "Feature",
    "geometry": {
        "type": "Point",
        "coordinates": [
            -110.84833333333333,
            31.695833333333333
        ]
    },
    "properties": {
        "feet": null,
        "meters": null,
        "latitude": 31.695833333333333,
        "longitude": -110.84833333333333,
        "name": "Mount Wrightson",
        "regions": [],
        "countries": [
            "United States"
        ],
        "continent": "North America",
        "marker-size": "large",
        "marker-symbol": "triangle",
        "state": "Arizona"
    }
}