{
    "type": "Feature",
    "geometry": {
        "type": "Point",
        "coordinates": [
            -110.82138888888889,
            33.2825
        ]
    },
    "properties": {
        "feet": null,
        "meters": null,
        "latitude": 33.2825,
        "longitude": -110.82138888888889,
        "name": "Pinal Peak",
        "regions": [],
        "countries": [
            "United States"
        ],
        "continent": "North America",
        "marker-size": "large",
        "marker-symbol": "triangle",
        "state": "Arizona"
    }
}