{
  "type": "Feature",
  "geometry": {
    "type": "Point",
    "coordinates": [
      -4.81763,
      56.2376
    ]
  },
  "properties": {
    "feet": 3317,
    "meters": 1011,
    "latitude": 56.2376,
    "longitude": -4.81763,
    "name": "Beinn Ime",
    "regions": [
      "United Kingdom, Ireland, & Iceland",
      "Scottish Highlands"
    ],
    "countries": [
      "United Kingdom"
    ],
    "continent": "Europe",
    "marker-size": "medium",
    "marker-symbol": "triangle"
  }
}
