{
  "type": "Feature",
  "geometry": {
    "type": "Point",
    "coordinates": [
      -4.465513,
      56.813189
    ]
  },
  "properties": {
    "feet": 3766,
    "meters": 1148,
    "latitude": 56.813189,
    "longitude": -4.465513,
    "name": "Ben Alder",
    "regions": [
      "United Kingdom, Ireland, & Iceland",
      "Scottish Highlands"
    ],
    "countries": [
      "United Kingdom"
    ],
    "continent": "Europe",
    "marker-size": "medium",
    "marker-symbol": "triangle"
  }
}
