{
  "type": "Feature",
  "geometry": {
    "type": "Point",
    "coordinates": [
      -3.437133,
      51.884333
    ]
  },
  "properties": {
    "feet": 2864,
    "meters": 873,
    "latitude": 51.884333,
    "longitude": -3.437133,
    "name": "Corn Du",
    "regions": [
      "United Kingdom, Ireland, & Iceland"
    ],
    "countries": [
      "United Kingdom"
    ],
    "continent": "Europe",
    "marker-size": "medium",
    "marker-symbol": "triangle"
  }
}
