{
  "type": "Feature",
  "geometry": {
    "type": "Point",
    "coordinates": [
      -3.19414,
      54.4649
    ]
  },
  "properties": {
    "feet": 2985,
    "meters": 910,
    "latitude": 54.4649,
    "longitude": -3.19414,
    "name": "Great End",
    "regions": [
      "United Kingdom, Ireland, & Iceland",
      "Lake District"
    ],
    "countries": [
      "United Kingdom"
    ],
    "continent": "Europe",
    "marker-size": "medium",
    "marker-symbol": "triangle"
  }
}
