{
  "type": "Feature",
  "geometry": {
    "type": "Point",
    "coordinates": [
      -6.13329,
      57.2492
    ]
  },
  "properties": {
    "feet": 2414,
    "meters": 736,
    "latitude": 57.2492,
    "longitude": -6.13329,
    "name": "Marsco",
    "regions": [
      "United Kingdom, Ireland, & Iceland",
      "Scottish Highlands"
    ],
    "countries": [
      "United Kingdom"
    ],
    "continent": "Europe",
    "marker-size": "medium",
    "marker-symbol": "triangle"
  }
}
