{
  "type": "Feature",
  "geometry": {
    "type": "Point",
    "coordinates": [
      -6.22247,
      57.2068
    ]
  },
  "properties": {
    "feet": 3208,
    "meters": 978,
    "latitude": 57.2068,
    "longitude": -6.22247,
    "name": "Sgurr Thearlaich",
    "regions": [
      "United Kingdom, Ireland, & Iceland",
      "Scottish Highlands"
    ],
    "countries": [
      "United Kingdom"
    ],
    "continent": "Europe",
    "marker-size": "medium",
    "marker-symbol": "triangle"
  }
}
