{
  "type": "Feature",
  "geometry": {
    "type": "Point",
    "coordinates": [
      76.020584,
      33.98077
    ]
  },
  "properties": {
    "feet": 23410,
    "meters": 7135,
    "latitude": 33.98077,
    "longitude": 76.020584,
    "name": "Nun Kun",
    "regions": [
      "Himalaya ",
      "Punjab Himalaya"
    ],
    "countries": [
      "India"
    ],
    "continent": "Asia",
    "marker-size": "large",
    "marker-symbol": "triangle"
  }
}
