{
    "type": "Feature",
    "geometry": {
        "type": "Point",
        "coordinates": [
            -105.41694444444445,
            36.55694444444444
        ]
    },
    "properties": {
        "feet": null,
        "meters": null,
        "latitude": 36.55694444444444,
        "longitude": -105.41694444444445,
        "name": "Wheeler Peak",
        "regions": [],
        "countries": [
            "United States"
        ],
        "continent": "North America",
        "marker-size": "large",
        "marker-symbol": "triangle",
        "state": "New Mexico"
    }
}