{
  "type": "Feature",
  "geometry": {
    "type": "Point",
    "coordinates": [
      10.25,
      47.2667
    ]
  },
  "properties": {
    "feet": 8527,
    "meters": 2599,
    "latitude": 47.2667,
    "longitude": 10.25,
    "name": "Biberkopf",
    "regions": [
      "Northern Alps"
    ],
    "countries": [
      "Germany"
    ],
    "continent": "Europe",
    "marker-size": "medium",
    "marker-symbol": "triangle"
  }
}
