{
  "type": "Feature",
  "geometry": {
    "type": "Point",
    "coordinates": [
      12.974339,
      47.675097
    ]
  },
  "properties": {
    "feet": 5265,
    "meters": 1605,
    "latitude": 47.675097,
    "longitude": 12.974339,
    "name": "Gr. Rauhenkopf",
    "regions": [
      "Northern Alps",
      "Bavarian Alps"
    ],
    "countries": [
      "Germany"
    ],
    "continent": "Europe",
    "marker-size": "medium",
    "marker-symbol": "triangle"
  }
}
