{
  "type": "Feature",
  "geometry": {
    "type": "Point",
    "coordinates": [
      12.0225,
      65.4466
    ]
  },
  "properties": {
    "feet": 3343,
    "meters": 1019,
    "latitude": 65.4466,
    "longitude": 12.0225,
    "name": "Grytfoten",
    "regions": [
      "Scandinavia/European Arctic"
    ],
    "countries": [
      "Norway"
    ],
    "continent": "Europe",
    "marker-size": "medium",
    "marker-symbol": "triangle"
  }
}
