{
  "type": "Feature",
  "geometry": {
    "type": "Point",
    "coordinates": [
      -61.416667,
      10.733333
    ]
  },
  "properties": {
    "feet": 3072,
    "meters": 936,
    "latitude": 10.733333,
    "longitude": -61.416667,
    "name": "El Tucuche",
    "regions": [
      "South Coastal Caribbean"
    ],
    "countries": [
      "Trinidad and Tobago"
    ],
    "continent": "South America",
    "marker-size": "medium",
    "marker-symbol": "triangle"
  }
}
