{
  "type": "Feature",
  "geometry": {
    "type": "Point",
    "coordinates": [
      87.825,
      49.149167
    ]
  },
  "properties": {
    "feet": 14350,
    "meters": 4374,
    "latitude": 49.149167,
    "longitude": 87.825,
    "name": "Khuiten Uul",
    "regions": [
      "Mongolia Ranges",
      "Altai"
    ],
    "countries": [
      "Mongolia",
      "China"
    ],
    "continent": "Asia",
    "marker-size": "large",
    "marker-symbol": "triangle"
  }
}
