{
    "type": "Feature",
    "geometry": {
        "type": "Point",
        "coordinates": [
            -128.0456,
            53.9397
        ]
    },
    "properties": {
        "feet": null,
        "meters": null,
        "latitude": 53.9397,
        "longitude": -128.0456,
        "name": "Atna Peak",
        "regions": [],
        "countries": [
            "Canada"
        ],
        "continent": "North America",
        "marker-size": "large",
        "marker-symbol": "triangle"
    }
}