{
    "type": "Feature",
    "geometry": {
        "type": "Point",
        "coordinates": [
            -128.045556,
            53.939722
        ]
    },
    "properties": {
        "feet": 8937.00816,
        "meters": 2724.0,
        "latitude": 53.939722,
        "longitude": -128.045556,
        "name": "Atna Peak",
        "countries": [
            "Canada"
        ],
        "continent": "North America",
        "marker-size": "medium",
        "marker-symbol": "triangle"
    }
}