{
    "type": "Feature",
    "geometry": {
        "type": "Point",
        "coordinates": [
            -122.50944,
            50.71667
        ]
    },
    "properties": {
        "feet": 9573.49112,
        "meters": 2918.0,
        "latitude": 50.71667,
        "longitude": -122.50944,
        "name": "Bendor Range",
        "countries": [
            "Canada"
        ],
        "continent": "North America",
        "marker-size": "medium",
        "marker-symbol": "triangle"
    }
}