{
    "type": "Feature",
    "geometry": {
        "type": "Point",
        "coordinates": [
            -66.42278,
            47.195
        ]
    },
    "properties": {
        "feet": 2204.72448,
        "meters": 672.0,
        "latitude": 47.195,
        "longitude": -66.42278,
        "name": "Big Bald Mountain",
        "countries": [
            "Canada"
        ],
        "continent": "North America",
        "marker-size": "medium",
        "marker-symbol": "triangle"
    }
}