{
    "type": "Feature",
    "geometry": {
        "type": "Point",
        "coordinates": [
            -122.955,
            49.98583
        ]
    },
    "properties": {
        "feet": 7424.54092,
        "meters": 2263.0,
        "latitude": 49.98583,
        "longitude": -122.955,
        "name": "Corrie Peak",
        "countries": [
            "Canada"
        ],
        "continent": "North America",
        "marker-size": "medium",
        "marker-symbol": "triangle"
    }
}