{
  "type": "Feature",
  "geometry": {
    "type": "Point",
    "coordinates": [
      -114.574013,
      49.704944
    ]
  },
  "properties": {
    "feet": 9137,
    "meters": 2785,
    "latitude": 49.704944,
    "longitude": -114.574013,
    "name": "Crowsnest Mountain",
    "regions": [
      "Rocky Mountains",
      "Canadian Rockies"
    ],
    "countries": [
      "Canada"
    ],
    "continent": "North America",
    "marker-size": "medium",
    "marker-symbol": "triangle"
  }
}
