{
    "type": "Feature",
    "geometry": {
        "type": "Point",
        "coordinates": [
            -114.57389,
            49.70361
        ]
    },
    "properties": {
        "feet": 9137.1394,
        "meters": 2785.0,
        "latitude": 49.70361,
        "longitude": -114.57389,
        "name": "Crowsnest Mountain",
        "countries": [
            "Canada"
        ],
        "continent": "North America",
        "marker-size": "medium",
        "marker-symbol": "triangle"
    }
}