{
    "type": "Feature",
    "geometry": {
        "type": "Point",
        "coordinates": [
            -116.43333,
            51.625
        ]
    },
    "properties": {
        "feet": 10022.9662,
        "meters": 3055.0,
        "latitude": 51.625,
        "longitude": -116.43333,
        "name": "Crowfoot Mountain",
        "countries": [
            "Canada"
        ],
        "continent": "North America",
        "marker-size": "medium",
        "marker-symbol": "triangle"
    }
}