{
    "type": "Feature",
    "geometry": {
        "type": "Point",
        "coordinates": [
            -133.3678,
            61.9225
        ]
    },
    "properties": {
        "feet": null,
        "meters": null,
        "latitude": 61.9225,
        "longitude": -133.3678,
        "name": "Fox Mountain",
        "regions": [],
        "countries": [
            "Canada"
        ],
        "continent": "North America",
        "marker-size": "large",
        "marker-symbol": "triangle"
    }
}