{
    "type": "Feature",
    "geometry": {
        "type": "Point",
        "coordinates": [
            -125.7469,
            49.6628
        ]
    },
    "properties": {
        "feet": null,
        "meters": null,
        "latitude": 49.6628,
        "longitude": -125.7469,
        "name": "Golden Hinde",
        "regions": [],
        "countries": [
            "Canada"
        ],
        "continent": "North America",
        "marker-size": "large",
        "marker-symbol": "triangle"
    }
}