{
  "type": "Feature",
  "geometry": {
    "type": "Point",
    "coordinates": [
      -57.7833,
      49.5833
    ]
  },
  "properties": {
    "feet": 2648,
    "meters": 807,
    "latitude": 49.5833,
    "longitude": -57.7833,
    "name": "Gros Morne",
    "regions": [
      "Appalachian Mountains",
      "Canadian Appalachians"
    ],
    "countries": [
      "Canada"
    ],
    "continent": "North America",
    "marker-size": "medium",
    "marker-symbol": "triangle"
  }
}
