{
    "type": "Feature",
    "geometry": {
        "type": "Point",
        "coordinates": [
            -116.23667,
            51.38333
        ]
    },
    "properties": {
        "feet": 10072.1788,
        "meters": 3070.0,
        "latitude": 51.38333,
        "longitude": -116.23667,
        "name": "Haddo Peak",
        "countries": [
            "Canada"
        ],
        "continent": "North America",
        "marker-size": "medium",
        "marker-symbol": "triangle"
    }
}