{
    "type": "Feature",
    "geometry": {
        "type": "Point",
        "coordinates": [
            -115.95167,
            51.10333
        ]
    },
    "properties": {
        "feet": 9580.0528,
        "meters": 2920.0,
        "latitude": 51.10333,
        "longitude": -115.95167,
        "name": "Haiduk Peak",
        "countries": [
            "Canada"
        ],
        "continent": "North America",
        "marker-size": "medium",
        "marker-symbol": "triangle"
    }
}