{
    "type": "Feature",
    "geometry": {
        "type": "Point",
        "coordinates": [
            -71.651694,
            70.799194
        ]
    },
    "properties": {
        "feet": 6250.0002,
        "meters": 1905.0,
        "latitude": 70.799194,
        "longitude": -71.651694,
        "name": "Kisimngiuqtuq Peak",
        "countries": [
            "Canada"
        ],
        "continent": "North America",
        "marker-size": "medium",
        "marker-symbol": "triangle",
        "states": [
            "Nunavut"
        ]
    }
}