{
    "type": "Feature",
    "geometry": {
        "type": "Point",
        "coordinates": [
            -117.38917,
            52.57944
        ]
    },
    "properties": {
        "feet": 10662.73,
        "meters": 3250.0,
        "latitude": 52.57944,
        "longitude": -117.38917,
        "name": "Monkhead",
        "countries": [
            "Canada"
        ],
        "continent": "North America",
        "marker-size": "medium",
        "marker-symbol": "triangle"
    }
}