{
    "type": "Feature",
    "geometry": {
        "type": "Point",
        "coordinates": [
            -65.9425,
            48.99056
        ]
    },
    "properties": {
        "feet": 4160.10512,
        "meters": 1268.0,
        "latitude": 48.99056,
        "longitude": -65.9425,
        "name": "Mont Jacques-Cartier",
        "countries": [
            "Canada"
        ],
        "continent": "North America",
        "marker-size": "medium",
        "marker-symbol": "triangle",
        "states": [
            "Quebec"
        ]
    }
}