{
  "type": "Feature",
  "geometry": {
    "type": "Point",
    "coordinates": [
      -63.7167,
      58.7167
    ]
  },
  "properties": {
    "feet": 5420,
    "meters": 1652,
    "latitude": 58.7167,
    "longitude": -63.7167,
    "name": "Mont Iberville",
    "regions": [
      "North American Plains",
      "Canadian Shield"
    ],
    "countries": [
      "Canada"
    ],
    "continent": "North America",
    "marker-size": "medium",
    "marker-symbol": "triangle"
  }
}
