{
    "type": "Feature",
    "geometry": {
        "type": "Point",
        "coordinates": [
            -73.05472,
            45.47667
        ]
    },
    "properties": {
        "feet": 1279.5276,
        "meters": 390.0,
        "latitude": 45.47667,
        "longitude": -73.05472,
        "name": "Mont Rougemont",
        "countries": [
            "Canada"
        ],
        "continent": "North America",
        "marker-size": "small",
        "marker-symbol": "triangle"
    }
}