{
    "type": "Feature",
    "geometry": {
        "type": "Point",
        "coordinates": [
            -65.9483,
            48.9878
        ]
    },
    "properties": {
        "feet": null,
        "meters": null,
        "latitude": 48.9878,
        "longitude": -65.9483,
        "name": "Mont Jacques-Cartier",
        "regions": [],
        "countries": [
            "Canada"
        ],
        "continent": "North America",
        "marker-size": "large",
        "marker-symbol": "triangle"
    }
}