{
    "type": "Feature",
    "geometry": {
        "type": "Point",
        "coordinates": [
            -71.91417,
            45.38028
        ]
    },
    "properties": {
        "feet": 1092.51972,
        "meters": 333.0,
        "latitude": 45.38028,
        "longitude": -71.91417,
        "name": "Mont Bellevue",
        "countries": [
            "Canada"
        ],
        "continent": "North America",
        "marker-size": "small",
        "marker-symbol": "triangle",
        "states": [
            "Quebec"
        ]
    }
}