{
    "type": "Feature",
    "geometry": {
        "type": "Point",
        "coordinates": [
            -116.22,
            51.2925
        ]
    },
    "properties": {
        "feet": 10859.5804,
        "meters": 3310.0,
        "latitude": 51.2925,
        "longitude": -116.22,
        "name": "Mount Allen",
        "countries": [
            "Canada"
        ],
        "continent": "North America",
        "marker-size": "medium",
        "marker-symbol": "triangle"
    }
}