{
    "type": "Feature",
    "geometry": {
        "type": "Point",
        "coordinates": [
            -116.675,
            51.93306
        ]
    },
    "properties": {
        "feet": 11000.65652,
        "meters": 3353.0,
        "latitude": 51.93306,
        "longitude": -116.675,
        "name": "Mount Murchison",
        "countries": [
            "Canada"
        ],
        "continent": "North America",
        "marker-size": "medium",
        "marker-symbol": "triangle"
    }
}