{
    "type": "Feature",
    "geometry": {
        "type": "Point",
        "coordinates": [
            -117.4417,
            52.1472
        ]
    },
    "properties": {
        "feet": null,
        "meters": null,
        "latitude": 52.1472,
        "longitude": -117.4417,
        "name": "Mount Columbia",
        "regions": [],
        "countries": [
            "Canada"
        ],
        "continent": "North America",
        "marker-size": "large",
        "marker-symbol": "triangle"
    }
}