{
  "type": "Feature",
  "geometry": {
    "type": "Point",
    "coordinates": [
      -117.426167,
      52.297142
    ]
  },
  "properties": {
    "feet": 11171,
    "meters": 3405,
    "latitude": 52.297142,
    "longitude": -117.426167,
    "name": "Mount Woolley",
    "regions": [
      "Rocky Mountains",
      "Canadian Rockies"
    ],
    "countries": [
      "Canada"
    ],
    "continent": "North America",
    "marker-size": "medium",
    "marker-symbol": "triangle"
  }
}
