{
    "type": "Feature",
    "geometry": {
        "type": "Point",
        "coordinates": [
            -116.57417,
            51.74778
        ]
    },
    "properties": {
        "feet": 10488.84548,
        "meters": 3197.0,
        "latitude": 51.74778,
        "longitude": -116.57417,
        "name": "Mount Patterson",
        "countries": [
            "Canada"
        ],
        "continent": "North America",
        "marker-size": "medium",
        "marker-symbol": "triangle"
    }
}