{
    "type": "Feature",
    "geometry": {
        "type": "Point",
        "coordinates": [
            -122.44361,
            50.32639
        ]
    },
    "properties": {
        "feet": 9130.57772,
        "meters": 2783.0,
        "latitude": 50.32639,
        "longitude": -122.44361,
        "name": "Mount Matier",
        "countries": [
            "Canada"
        ],
        "continent": "North America",
        "marker-size": "medium",
        "marker-symbol": "triangle"
    }
}