{
  "type": "Feature",
  "geometry": {
    "type": "Point",
    "coordinates": [
      -125.867222,
      49.749444
    ]
  },
  "properties": {
    "feet": 7201,
    "meters": 2195,
    "latitude": 49.749444,
    "longitutde": -125.867222,
    "name": "Mount Colonel Foster",
    "regions": [
      "Pacific Ranges",
      "British Columbia Coast Ranges"
    ],
    "countries": [
      "Canada"
    ],
    "continent": "North America",
    "marker-size": "medium",
    "marker-symbol": "triangle"
  }
}
