{
  "type": "Feature",
  "geometry": {
    "type": "Point",
    "coordinates": [
      -116.767,
      51.8917
    ]
  },
  "properties": {
    "feet": 10351,
    "meters": 3155,
    "latitude": 51.8917,
    "longitude": -116.767,
    "name": "Mount Sarbach",
    "regions": [
      "Rocky Mountains",
      "Canadian Rockies"
    ],
    "countries": [
      "Canada"
    ],
    "continent": "North America",
    "marker-size": "medium",
    "marker-symbol": "triangle"
  }
}
