{
    "type": "Feature",
    "geometry": {
        "type": "Point",
        "coordinates": [
            -115.47028,
            51.12417
        ]
    },
    "properties": {
        "feet": 9671.91632,
        "meters": 2948.0,
        "latitude": 51.12417,
        "longitude": -115.47028,
        "name": "Mount Rundle",
        "countries": [
            "Canada"
        ],
        "continent": "North America",
        "marker-size": "medium",
        "marker-symbol": "triangle"
    }
}