{
    "type": "Feature",
    "geometry": {
        "type": "Point",
        "coordinates": [
            -116.76806,
            51.89278
        ]
    },
    "properties": {
        "feet": 10351.0502,
        "meters": 3155.0,
        "latitude": 51.89278,
        "longitude": -116.76806,
        "name": "Mount Sarbach",
        "countries": [
            "Canada"
        ],
        "continent": "North America",
        "marker-size": "medium",
        "marker-symbol": "triangle"
    }
}