{
    "type": "Feature",
    "geometry": {
        "type": "Point",
        "coordinates": [
            -115.38694,
            50.80778
        ]
    },
    "properties": {
        "feet": 9639.10792,
        "meters": 2938.0,
        "latitude": 50.80778,
        "longitude": -115.38694,
        "name": "Mount Smuts",
        "countries": [
            "Canada"
        ],
        "continent": "North America",
        "marker-size": "medium",
        "marker-symbol": "triangle"
    }
}