{
    "type": "Feature",
    "geometry": {
        "type": "Point",
        "coordinates": [
            -117.42528,
            52.29722
        ]
    },
    "properties": {
        "feet": 11171.2602,
        "meters": 3405.0,
        "latitude": 52.29722,
        "longitude": -117.42528,
        "name": "Mount Woolley",
        "countries": [
            "Canada"
        ],
        "continent": "North America",
        "marker-size": "medium",
        "marker-symbol": "triangle"
    }
}