{
    "type": "Feature",
    "geometry": {
        "type": "Point",
        "coordinates": [
            -114.82639,
            50.39111
        ]
    },
    "properties": {
        "feet": 9048.55672,
        "meters": 2758.0,
        "latitude": 50.39111,
        "longitude": -114.82639,
        "name": "Mount Muir",
        "countries": [
            "Canada"
        ],
        "continent": "North America",
        "marker-size": "medium",
        "marker-symbol": "triangle"
    }
}