{
  "type": "Feature",
  "geometry": {
    "type": "Point",
    "coordinates": [
      -116.575241,
      51.746376
    ]
  },
  "properties": {
    "feet": 10489,
    "meters": 3197,
    "latitude": 51.746376,
    "longitude": -116.575241,
    "name": "Mount Patterson",
    "regions": [
      "Rocky Mountains",
      "Canadian Rockies"
    ],
    "countries": [
      "Canada"
    ],
    "continent": "North America",
    "marker-size": "medium",
    "marker-symbol": "triangle"
  }
}
