{
    "type": "Feature",
    "geometry": {
        "type": "Point",
        "coordinates": [
            -117.32917,
            52.04
        ]
    },
    "properties": {
        "feet": 11505.90588,
        "meters": 3507.0,
        "latitude": 52.04,
        "longitude": -117.32917,
        "name": "Mount Bryce",
        "countries": [
            "Canada"
        ],
        "continent": "North America",
        "marker-size": "medium",
        "marker-symbol": "triangle"
    }
}