{
    "type": "Feature",
    "geometry": {
        "type": "Point",
        "coordinates": [
            -125.2636,
            51.3736
        ]
    },
    "properties": {
        "feet": null,
        "meters": null,
        "latitude": 51.3736,
        "longitude": -125.2636,
        "name": "Mount Waddington",
        "regions": [],
        "countries": [
            "Canada"
        ],
        "continent": "North America",
        "marker-size": "large",
        "marker-symbol": "triangle"
    }
}