{
    "type": "Feature",
    "geometry": {
        "type": "Point",
        "coordinates": [
            -118.018056,
            52.458611
        ]
    },
    "properties": {
        "feet": 9842.52,
        "meters": 3000.0,
        "latitude": 52.458611,
        "longitude": -118.018056,
        "name": "Mount Ross Cox",
        "countries": [
            "Canada"
        ],
        "continent": "North America",
        "marker-size": "medium",
        "marker-symbol": "triangle"
    }
}