{
    "type": "Feature",
    "geometry": {
        "type": "Point",
        "coordinates": [
            -129.0564,
            54.275
        ]
    },
    "properties": {
        "feet": null,
        "meters": null,
        "latitude": 54.275,
        "longitude": -129.0564,
        "name": "Mount Valpy",
        "regions": [],
        "countries": [
            "Canada"
        ],
        "continent": "North America",
        "marker-size": "large",
        "marker-symbol": "triangle"
    }
}