{
    "type": "Feature",
    "geometry": {
        "type": "Point",
        "coordinates": [
            -125.86722,
            49.74944
        ]
    },
    "properties": {
        "feet": 7004.5934,
        "meters": 2135.0,
        "latitude": 49.74944,
        "longitude": -125.86722,
        "name": "Mount Colonel Foster",
        "countries": [
            "Canada"
        ],
        "continent": "North America",
        "marker-size": "medium",
        "marker-symbol": "triangle"
    }
}