{
    "type": "Feature",
    "geometry": {
        "type": "Point",
        "coordinates": [
            -116.92111,
            51.95972
        ]
    },
    "properties": {
        "feet": 10711.9426,
        "meters": 3265.0,
        "latitude": 51.95972,
        "longitude": -116.92111,
        "name": "Mount Erasmus",
        "countries": [
            "Canada"
        ],
        "continent": "North America",
        "marker-size": "medium",
        "marker-symbol": "triangle"
    }
}