{
    "type": "Feature",
    "geometry": {
        "type": "Point",
        "coordinates": [
            -116.10111,
            51.28417
        ]
    },
    "properties": {
        "feet": 9547.2444,
        "meters": 2910.0,
        "latitude": 51.28417,
        "longitude": -116.10111,
        "name": "Mount Bell",
        "countries": [
            "Canada"
        ],
        "continent": "North America",
        "marker-size": "medium",
        "marker-symbol": "triangle"
    }
}