{
  "type": "Feature",
  "geometry": {
    "type": "Point",
    "coordinates": [
      -115.41,
      50.8281
    ]
  },
  "properties": {
    "feet": 9140,
    "meters": 2786,
    "latitude": 50.8281,
    "longitude": -115.41,
    "name": "Mount Shark",
    "regions": [
      "Rocky Mountains",
      "Canadian Rockies"
    ],
    "countries": [
      "Canada"
    ],
    "continent": "North America",
    "marker-size": "medium",
    "marker-symbol": "triangle"
  }
}
