{
  "type": "Feature",
  "geometry": {
    "type": "Point",
    "coordinates": [
      -114.974,
      50.6223
    ]
  },
  "properties": {
    "feet": 10558,
    "meters": 3218,
    "latitude": 50.6223,
    "longitude": -114.974,
    "name": "Mount Rae",
    "regions": [
      "Rocky Mountains",
      "Canadian Rockies"
    ],
    "countries": [
      "Canada"
    ],
    "continent": "North America",
    "marker-size": "medium",
    "marker-symbol": "triangle"
  }
}
