{
    "type": "Feature",
    "geometry": {
        "type": "Point",
        "coordinates": [
            -117.45,
            52.33639
        ]
    },
    "properties": {
        "feet": 10269.029199999999,
        "meters": 3130.0,
        "latitude": 52.33639,
        "longitude": -117.45,
        "name": "Mount GEC",
        "countries": [
            "Canada"
        ],
        "continent": "North America",
        "marker-size": "medium",
        "marker-symbol": "triangle"
    }
}