{
    "type": "Feature",
    "geometry": {
        "type": "Point",
        "coordinates": [
            -122.92722,
            49.43028
        ]
    },
    "properties": {
        "feet": 4950.78756,
        "meters": 1509.0,
        "latitude": 49.43028,
        "longitude": -122.92722,
        "name": "Mount Bishop",
        "countries": [
            "Canada"
        ],
        "continent": "North America",
        "marker-size": "medium",
        "marker-symbol": "triangle"
    }
}