{
    "type": "Feature",
    "geometry": {
        "type": "Point",
        "coordinates": [
            -117.44167,
            52.14722
        ]
    },
    "properties": {
        "feet": 12293.30748,
        "meters": 3747.0,
        "latitude": 52.14722,
        "longitude": -117.44167,
        "name": "Mount Columbia",
        "countries": [
            "Canada"
        ],
        "continent": "North America",
        "marker-size": "medium",
        "marker-symbol": "triangle"
    }
}