{
    "type": "Feature",
    "geometry": {
        "type": "Point",
        "coordinates": [
            -116.53,
            51.25861
        ]
    },
    "properties": {
        "feet": 10859.5804,
        "meters": 3310.0,
        "latitude": 51.25861,
        "longitude": -116.53,
        "name": "Mount Vaux",
        "countries": [
            "Canada"
        ],
        "continent": "North America",
        "marker-size": "medium",
        "marker-symbol": "triangle"
    }
}