{
    "type": "Feature",
    "geometry": {
        "type": "Point",
        "coordinates": [
            -116.46694,
            51.74222
        ]
    },
    "properties": {
        "feet": 10413.38616,
        "meters": 3174.0,
        "latitude": 51.74222,
        "longitude": -116.46694,
        "name": "Observation Peak",
        "countries": [
            "Canada"
        ],
        "continent": "North America",
        "marker-size": "medium",
        "marker-symbol": "triangle"
    }
}