{
    "type": "Feature",
    "geometry": {
        "type": "Point",
        "coordinates": [
            -122.80722,
            50.14667
        ]
    },
    "properties": {
        "feet": 8182.41496,
        "meters": 2494.0,
        "latitude": 50.14667,
        "longitude": -122.80722,
        "name": "Parkhurst Mountain",
        "countries": [
            "Canada"
        ],
        "continent": "North America",
        "marker-size": "medium",
        "marker-symbol": "triangle"
    }
}