{
    "type": "Feature",
    "geometry": {
        "type": "Point",
        "coordinates": [
            -122.93972,
            49.93361
        ]
    },
    "properties": {
        "feet": 8257.87428,
        "meters": 2517.0,
        "latitude": 49.93361,
        "longitude": -122.93972,
        "name": "Phyllis%27s Engine",
        "countries": [
            "Canada"
        ],
        "continent": "North America",
        "marker-size": "medium",
        "marker-symbol": "triangle"
    }
}