{
    "type": "Feature",
    "geometry": {
        "type": "Point",
        "coordinates": [
            -116.51528,
            51.65778
        ]
    },
    "properties": {
        "feet": 9599.73784,
        "meters": 2926.0,
        "latitude": 51.65778,
        "longitude": -116.51528,
        "name": "Portal Peak",
        "countries": [
            "Canada"
        ],
        "continent": "North America",
        "marker-size": "medium",
        "marker-symbol": "triangle"
    }
}