{
    "type": "Feature",
    "geometry": {
        "type": "Point",
        "coordinates": [
            -115.36889,
            51.15889
        ]
    },
    "properties": {
        "feet": 8251.3126,
        "meters": 2515.0,
        "latitude": 51.15889,
        "longitude": -115.36889,
        "name": "Princess Margaret Mountain",
        "countries": [
            "Canada"
        ],
        "continent": "North America",
        "marker-size": "medium",
        "marker-symbol": "triangle"
    }
}