{
    "type": "Feature",
    "geometry": {
        "type": "Point",
        "coordinates": [
            -75.90667,
            72.1825
        ]
    },
    "properties": {
        "feet": 6440.28892,
        "meters": 1963.0,
        "latitude": 72.1825,
        "longitude": -75.90667,
        "name": "Qiajivik Mountain",
        "countries": [
            "Canada"
        ],
        "continent": "North America",
        "marker-size": "medium",
        "marker-symbol": "triangle",
        "states": [
            "Nunavut"
        ]
    }
}