{
    "type": "Feature",
    "geometry": {
        "type": "Point",
        "coordinates": [
            -127.24,
            53.0072
        ]
    },
    "properties": {
        "feet": null,
        "meters": null,
        "latitude": 53.0072,
        "longitude": -127.24,
        "name": "Sharks Teeth Peaks",
        "regions": [],
        "countries": [
            "Canada"
        ],
        "continent": "North America",
        "marker-size": "large",
        "marker-symbol": "triangle"
    }
}