{
    "type": "Feature",
    "geometry": {
        "type": "Point",
        "coordinates": [
            -116.05417,
            51.17056
        ]
    },
    "properties": {
        "feet": 10351.0502,
        "meters": 3155.0,
        "latitude": 51.17056,
        "longitude": -116.05417,
        "name": "Stanley Peak",
        "countries": [
            "Canada"
        ],
        "continent": "North America",
        "marker-size": "medium",
        "marker-symbol": "triangle"
    }
}