{
    "type": "Feature",
    "geometry": {
        "type": "Point",
        "coordinates": [
            -116.58889,
            50.41639
        ]
    },
    "properties": {
        "feet": 10728.3468,
        "meters": 3270.0,
        "latitude": 50.41639,
        "longitude": -116.58889,
        "name": "The Lieutenants",
        "countries": [
            "Canada"
        ],
        "continent": "North America",
        "marker-size": "medium",
        "marker-symbol": "triangle"
    }
}