{
  "type": "Feature",
  "geometry": {
    "type": "Point",
    "coordinates": [
      -116.593,
      50.4167
    ]
  },
  "properties": {
    "feet": 10735,
    "meters": 3272,
    "latitude": 50.4167,
    "longitude": -116.593,
    "name": "The Lieutenants",
    "regions": [
      "Intermountain West",
      "Southwest Basins and Ranges"
    ],
    "countries": [
      "Canada"
    ],
    "continent": "North America",
    "marker-size": "medium",
    "marker-symbol": "triangle"
  }
}
