{
    "type": "Feature",
    "geometry": {
        "type": "Point",
        "coordinates": [
            -122.80472,
            50.05528
        ]
    },
    "properties": {
        "feet": 8828.74044,
        "meters": 2691.0,
        "latitude": 50.05528,
        "longitude": -122.80472,
        "name": "Tremor Mountain",
        "countries": [
            "Canada"
        ],
        "continent": "North America",
        "marker-size": "medium",
        "marker-symbol": "triangle"
    }
}