{
    "type": "Feature",
    "geometry": {
        "type": "Point",
        "coordinates": [
            -117.10222,
            51.95222
        ]
    },
    "properties": {
        "feet": 11158.13684,
        "meters": 3401.0,
        "latitude": 51.95222,
        "longitude": -117.10222,
        "name": "Walter Peak",
        "countries": [
            "Canada"
        ],
        "continent": "North America",
        "marker-size": "medium",
        "marker-symbol": "triangle"
    }
}