{
    "type": "Feature",
    "geometry": {
        "type": "Point",
        "coordinates": [
            -119.26667,
            53.13694
        ]
    },
    "properties": {
        "feet": 11151.57516,
        "meters": 3399.0,
        "latitude": 53.13694,
        "longitude": -119.26667,
        "name": "Whitehorn Mountain",
        "countries": [
            "Canada"
        ],
        "continent": "North America",
        "marker-size": "medium",
        "marker-symbol": "triangle"
    }
}