{
  "type": "Feature",
  "geometry": {
    "type": "Point",
    "coordinates": [
      22.0523,
      43.1351
    ]
  },
  "properties": {
    "feet": 3228,
    "meters": 984,
    "latitude": 43.1351,
    "longitude": 22.0523,
    "name": "Mosor - Suva planina",
    "regions": [
      "Balkan Peninsula",
      "Balkan Mountains"
    ],
    "countries": [
      "Serbia and Montenegro"
    ],
    "continent": "Europe",
    "marker-size": "medium",
    "marker-symbol": "triangle"
  }
}
