{
  "type": "Feature",
  "geometry": {
    "type": "Point",
    "coordinates": [
      13.97315,
      50.566938
    ]
  },
  "properties": {
    "feet": 2316,
    "meters": 706,
    "latitude": 50.566938,
    "longitude": 13.97315,
    "name": "Kletecna",
    "regions": [
      "Central Europe Ranges"
    ],
    "countries": [
      "Czech Republic"
    ],
    "continent": "Europe",
    "marker-size": "medium",
    "marker-symbol": "triangle"
  }
}
