{
    "type": "Feature",
    "geometry": {
        "type": "Point",
        "coordinates": [
            8.12722,
            46.53861
        ]
    },
    "properties": {
        "feet": 14022.310159999999,
        "meters": 4274.0,
        "latitude": 46.53861,
        "longitude": 8.12722,
        "name": "Bernese Alps",
        "countries": [
            "Switzerland"
        ],
        "continent": "Europe",
        "marker-size": "large",
        "marker-symbol": "triangle"
    }
}