{
  "type": "Feature",
  "geometry": {
    "type": "Point",
    "coordinates": [
      7.88333,
      45.9167
    ]
  },
  "properties": {
    "feet": 15203,
    "meters": 4634,
    "latitude": 45.9167,
    "longitude": 7.88333,
    "name": "Dufourspitze",
    "regions": [
      "Southern Alps",
      "Pennine Alps"
    ],
    "countries": [
      "Switzerland"
    ],
    "continent": "Europe",
    "marker-size": "large",
    "marker-symbol": "triangle"
  }
}
