{
  "type": "Feature",
  "geometry": {
    "type": "Point",
    "coordinates": [
      8.415589,
      46.603281
    ]
  },
  "properties": {
    "feet": 9455,
    "meters": 2882,
    "latitude": 46.603281,
    "longitude": 8.415589,
    "name": "Hannibal Turm",
    "regions": [
      "Northern Alps",
      "Urner Alps"
    ],
    "countries": [
      "Switzerland"
    ],
    "continent": "Europe",
    "marker-size": "medium",
    "marker-symbol": "triangle"
  }
}
