{
  "type": "Feature",
  "geometry": {
    "type": "Point",
    "coordinates": [
      7.729722,
      45.938333
    ]
  },
  "properties": {
    "feet": 12740,
    "meters": 3883,
    "latitude": 45.938333,
    "longitude": 7.729722,
    "name": "Klein Matterhorn",
    "regions": [
      "Western Alps"
    ],
    "countries": [
      "Switzerland"
    ],
    "continent": "Europe",
    "marker-size": "medium",
    "marker-symbol": "triangle"
  }
}
