{
  "type": "Feature",
  "geometry": {
    "type": "Point",
    "coordinates": [
      7.925833,
      46.413333
    ]
  },
  "properties": {
    "feet": 12539,
    "meters": 3822,
    "latitude": 46.413333,
    "longitude": 7.925833,
    "name": "Nesthorn",
    "regions": [
      "Northern Alps",
      "Berner Oberland"
    ],
    "countries": [
      "Switzerland"
    ],
    "continent": "Europe",
    "marker-size": "medium",
    "marker-symbol": "triangle"
  }
}
