{
  "type": "Feature",
  "geometry": {
    "type": "Point",
    "coordinates": [
      7.741542,
      46.055573
    ]
  },
  "properties": {
    "feet": 11870,
    "meters": 3618,
    "latitude": 46.055573,
    "longitude": 7.741542,
    "name": "Unter Aschhorn",
    "regions": [
      "Southern Alps",
      "Pennine Alps"
    ],
    "countries": [
      "Switzerland"
    ],
    "continent": "Europe",
    "marker-size": "medium",
    "marker-symbol": "triangle"
  }
}
