{
  "type": "Feature",
  "geometry": {
    "type": "Point",
    "coordinates": [
      7.43333,
      46.5333
    ]
  },
  "properties": {
    "feet": 7392,
    "meters": 2253,
    "latitude": 46.5333,
    "longitude": 7.43333,
    "name": "Vorderi Spillgerte",
    "countries": [
      "Switzerland"
    ],
    "continent": "Europe",
    "marker-size": "medium",
    "marker-symbol": "triangle"
  }
}
