{
    "type": "Feature",
    "geometry": {
        "type": "Point",
        "coordinates": [
            -48.917,
            62.817
        ]
    },
    "properties": {
        "feet": 5469.16028,
        "meters": 1667.0,
        "latitude": 62.817,
        "longitude": -48.917,
        "name": "J.A.D. Jensen Nunatakker",
        "countries": [
            "Greenland"
        ],
        "continent": "North America",
        "marker-size": "medium",
        "marker-symbol": "triangle"
    }
}