{
    "type": "Feature",
    "geometry": {
        "type": "Point",
        "coordinates": [
            -48.8483,
            62.7919
        ]
    },
    "properties": {
        "feet": null,
        "meters": null,
        "latitude": 62.7919,
        "longitude": -48.8483,
        "name": "J.A.D. Jensen Nunatakker",
        "regions": [],
        "countries": [
            "Greenland"
        ],
        "continent": "North America",
        "marker-size": "large",
        "marker-symbol": "triangle"
    }
}