{
  "type": "Feature",
  "geometry": {
    "type": "Point",
    "coordinates": [
      -37.342529,
      65.992329
    ]
  },
  "properties": {
    "feet": 4757,
    "meters": 1450,
    "latitude": 65.992329,
    "longitude": -37.342529,
    "name": "Nanu Sax",
    "regions": [
      "North American Arctic Islands",
      "Greenland"
    ],
    "countries": [
      "Greenland"
    ],
    "continent": "North America",
    "marker-size": "medium",
    "marker-symbol": "triangle"
  }
}
