{
    "type": "Feature",
    "geometry": {
        "type": "Point",
        "coordinates": [
            -52.9167,
            66.4333
        ]
    },
    "properties": {
        "feet": null,
        "meters": null,
        "latitude": 66.4333,
        "longitude": -52.9167,
        "name": "Parnaqussuit Qavaat high point",
        "regions": [],
        "countries": [
            "Greenland"
        ],
        "continent": "North America",
        "marker-size": "large",
        "marker-symbol": "triangle"
    }
}