{
    "type": "Feature",
    "geometry": {
        "type": "Point",
        "coordinates": [
            -51.1133,
            64.3914
        ]
    },
    "properties": {
        "feet": null,
        "meters": null,
        "latitude": 64.3914,
        "longitude": -51.1133,
        "name": "Salliaruseq high point",
        "regions": [],
        "countries": [
            "Greenland"
        ],
        "continent": "North America",
        "marker-size": "large",
        "marker-symbol": "triangle"
    }
}