{
    "type": "Feature",
    "geometry": {
        "type": "Point",
        "coordinates": [
            -24.0667,
            72.7167
        ]
    },
    "properties": {
        "feet": null,
        "meters": null,
        "latitude": 72.7167,
        "longitude": -24.0667,
        "name": "Traill Island high point",
        "regions": [],
        "countries": [
            "Greenland"
        ],
        "continent": "North America",
        "marker-size": "large",
        "marker-symbol": "triangle"
    }
}