{
    "type": "Feature",
    "geometry": {
        "type": "Point",
        "coordinates": [
            -76.8361,
            19.9897
        ]
    },
    "properties": {
        "feet": null,
        "meters": null,
        "latitude": 19.9897,
        "longitude": -76.8361,
        "name": "Pico Turquino",
        "regions": [],
        "countries": [
            "Cuba"
        ],
        "continent": "North America",
        "marker-size": "large",
        "marker-symbol": "triangle"
    }
}