{
  "type": "Feature",
  "geometry": {
    "type": "Point",
    "coordinates": [
      6.88722,
      45.87861
    ]
  },
  "properties": {
    "feet": 12605,
    "meters": 3842,
    "name": "Aiguille Du Midi",
    "regions": [
      "Western Alps",
      "Savoy Alps"
    ],
    "countries": [
      "France"
    ],
    "continent": "Europe",
    "marker-size": "medium",
    "marker-symbol": "triangle"
  }
}
