{
  "type": "Feature",
  "geometry": {
    "type": "Point",
    "coordinates": [
      7.00944,
      45.99417
    ]
  },
  "properties": {
    "feet": 11621,
    "meters": 3542,
    "name": "Aiguille Du Tour",
    "regions": [
      "Western Alps",
      "Savoy Alps"
    ],
    "countries": [
      "France",
      "Switzerland"
    ],
    "continent": "Europe",
    "marker-size": "medium",
    "marker-symbol": "triangle"
  }
}
