{
  "type": "Feature",
  "geometry": {
    "type": "Point",
    "coordinates": [
      6.91917,
      45.9025
    ]
  },
  "properties": {
    "feet": 11424,
    "meters": 3482,
    "name": "Aiguille Du Grépon",
    "regions": [
      "Western Alps",
      "Savoy Alps"
    ],
    "countries": [
      "France"
    ],
    "continent": "Europe",
    "marker-size": "medium",
    "marker-symbol": "triangle"
  }
}
