{
  "type": "Feature",
  "geometry": {
    "type": "Point",
    "coordinates": [
      7.39833,
      44.1222
    ]
  },
  "properties": {
    "feet": 10170,
    "meters": 3100,
    "name": "La Maledie",
    "regions": [
      "Western Alps",
      "Maritime Alps"
    ],
    "countries": [
      "France"
    ],
    "continent": "Europe",
    "marker-size": "medium",
    "marker-symbol": "triangle"
  }
}
