{
    "type": "Feature",
    "geometry": {
        "type": "Point",
        "coordinates": [
            -106.21805555555555,
            38.325
        ]
    },
    "properties": {
        "feet": null,
        "meters": null,
        "latitude": 38.325,
        "longitude": -106.21805555555555,
        "name": "Antora Peak",
        "regions": [],
        "countries": [
            "United States"
        ],
        "continent": "North America",
        "marker-size": "large",
        "marker-symbol": "triangle",
        "state": "Colorado"
    }
}