{
    "type": "Feature",
    "geometry": {
        "type": "Point",
        "coordinates": [
            -106.43416666666667,
            37.483333333333334
        ]
    },
    "properties": {
        "feet": null,
        "meters": null,
        "latitude": 37.483333333333334,
        "longitude": -106.43416666666667,
        "name": "Bennett Peak",
        "regions": [],
        "countries": [
            "United States"
        ],
        "continent": "North America",
        "marker-size": "large",
        "marker-symbol": "triangle",
        "state": "Colorado"
    }
}