{
    "type": "Feature",
    "geometry": {
        "type": "Point",
        "coordinates": [
            -105.88916666666667,
            38.34111111111111
        ]
    },
    "properties": {
        "feet": null,
        "meters": null,
        "latitude": 38.34111111111111,
        "longitude": -105.88916666666667,
        "name": "Bushnell Peak",
        "regions": [],
        "countries": [
            "United States"
        ],
        "continent": "North America",
        "marker-size": "large",
        "marker-symbol": "triangle",
        "state": "Colorado"
    }
}