{
  "type": "Feature",
  "geometry": {
    "type": "Point",
    "coordinates": [
      -105.492,
      37.5825
    ]
  },
  "properties": {
    "feet": 14042,
    "meters": 4280,
    "latitude": 37.5825,
    "longitude": -105.492,
    "name": "Ellingwood Point",
    "regions": [
      "Rocky Mountains",
      "Sangre de Cristo Range"
    ],
    "states": [
      "Colorado"
    ],
    "countries": [
      "United States"
    ],
    "continent": "North America",
    "marker-size": "large",
    "marker-symbol": "triangle"
  }
}
