{
    "type": "Feature",
    "geometry": {
        "type": "Point",
        "coordinates": [
            -106.64500000000001,
            38.83388888888889
        ]
    },
    "properties": {
        "feet": null,
        "meters": null,
        "latitude": 38.83388888888889,
        "longitude": -106.64500000000001,
        "name": "Matchless Mountain",
        "regions": [],
        "countries": [
            "United States"
        ],
        "continent": "North America",
        "marker-size": "large",
        "marker-symbol": "triangle",
        "state": "Colorado"
    }
}