{
    "type": "Feature",
    "geometry": {
        "type": "Point",
        "coordinates": [
            -105.6438064,
            39.5883155
        ]
    },
    "properties": {
        "feet": 14267.0,
        "meters": 4348.581460845393,
        "latitude": 39.5883155,
        "longitude": -105.6438064,
        "name": "Mount Evans",
        "countries": [
            "United States"
        ],
        "continent": "North America",
        "marker-size": "large",
        "marker-symbol": "triangle",
        "states": [
            "Colorado"
        ]
    }
}