{
  "type": "Feature",
  "geometry": {
    "type": "Point",
    "coordinates": [
      -105.668,
      39.5828
    ]
  },
  "properties": {
    "feet": 14060,
    "meters": 4286,
    "latitude": 39.5828,
    "longitude": -105.668,
    "name": "Mount Bierstadt",
    "regions": [
      "Rocky Mountains",
      "Front Range"
    ],
    "states": [
      "Colorado"
    ],
    "countries": [
      "United States"
    ],
    "continent": "North America",
    "marker-size": "large",
    "marker-symbol": "triangle"
  }
}
