{
  "type": "Feature",
  "geometry": {
    "type": "Point",
    "coordinates": [
      -105.616,
      40.0989
    ]
  },
  "properties": {
    "feet": 13565,
    "meters": 4135,
    "latitude": 40.0989,
    "longitude": -105.616,
    "name": "Mount Audubon",
    "regions": [
      "Rocky Mountains",
      "Front Range"
    ],
    "states": [
      "Colorado"
    ],
    "countries": [
      "United States"
    ],
    "continent": "North America",
    "marker-size": "medium",
    "marker-symbol": "triangle"
  }
}
