{
    "type": "Feature",
    "geometry": {
        "type": "Point",
        "coordinates": [
            -106.00527777777778,
            39.339444444444446
        ]
    },
    "properties": {
        "feet": null,
        "meters": null,
        "latitude": 39.339444444444446,
        "longitude": -106.00527777777778,
        "name": "Mount Silverheels",
        "regions": [],
        "countries": [
            "United States"
        ],
        "continent": "North America",
        "marker-size": "large",
        "marker-symbol": "triangle",
        "state": "Colorado"
    }
}