{
    "type": "Feature",
    "geometry": {
        "type": "Point",
        "coordinates": [
            -106.48166666666667,
            39.46666666666667
        ]
    },
    "properties": {
        "feet": null,
        "meters": null,
        "latitude": 39.46666666666667,
        "longitude": -106.48166666666667,
        "name": "Mount of the Holy Cross",
        "regions": [],
        "countries": [
            "United States"
        ],
        "continent": "North America",
        "marker-size": "large",
        "marker-symbol": "triangle",
        "state": "Colorado"
    }
}