{
  "type": "Feature",
  "geometry": {
    "type": "Point",
    "coordinates": [
      -106.005,
      39.3392
    ]
  },
  "properties": {
    "feet": 13822,
    "meters": 4213,
    "latitude": 39.3392,
    "longitude": -106.005,
    "name": "Mount Silverheels",
    "regions": [
      "Rocky Mountains",
      "Central Colorado Ranges"
    ],
    "states": [
      "Colorado"
    ],
    "countries": [
      "United States"
    ],
    "continent": "North America",
    "marker-size": "large",
    "marker-symbol": "triangle"
  }
}
