{
  "type": "Feature",
  "geometry": {
    "type": "Point",
    "coordinates": [
      -106.479,
      39.4681
    ]
  },
  "properties": {
    "feet": 14005,
    "meters": 4269,
    "latitude": 39.4681,
    "longitude": -106.479,
    "name": "Mount of the Holy Cross",
    "regions": [
      "Rocky Mountains",
      "Sawatch Range"
    ],
    "states": [
      "Colorado"
    ],
    "countries": [
      "United States"
    ],
    "continent": "North America",
    "marker-size": "large",
    "marker-symbol": "triangle"
  }
}
