{
    "type": "Feature",
    "geometry": {
        "type": "Point",
        "coordinates": [
            -106.0053607,
            39.3393949
        ]
    },
    "properties": {
        "feet": 13829.0,
        "meters": 4215.07906511747,
        "latitude": 39.3393949,
        "longitude": -106.0053607,
        "name": "Mount Silverheels",
        "countries": [
            "United States"
        ],
        "continent": "North America",
        "marker-size": "large",
        "marker-symbol": "triangle",
        "states": [
            "Colorado"
        ]
    }
}