{
    "type": "Feature",
    "geometry": {
        "type": "Point",
        "coordinates": [
            -105.6438888888889,
            39.58833333333334
        ]
    },
    "properties": {
        "feet": null,
        "meters": null,
        "latitude": 39.58833333333334,
        "longitude": -105.6438888888889,
        "name": "Mount Evans",
        "regions": [],
        "countries": [
            "United States"
        ],
        "continent": "North America",
        "marker-size": "large",
        "marker-symbol": "triangle",
        "state": "Colorado"
    }
}