{
    "type": "Feature",
    "geometry": {
        "type": "Point",
        "coordinates": [
            -107.79222222222222,
            38.00388888888889
        ]
    },
    "properties": {
        "feet": null,
        "meters": null,
        "latitude": 38.00388888888889,
        "longitude": -107.79222222222222,
        "name": "Mount Sneffels",
        "regions": [],
        "countries": [
            "United States"
        ],
        "continent": "North America",
        "marker-size": "large",
        "marker-symbol": "triangle",
        "state": "Colorado"
    }
}