{
    "type": "Feature",
    "geometry": {
        "type": "Point",
        "coordinates": [
            -108.77194444444444,
            38.82611111111112
        ]
    },
    "properties": {
        "feet": null,
        "meters": null,
        "latitude": 38.82611111111112,
        "longitude": -108.77194444444444,
        "name": "Pi\u00f1on Mesa HP",
        "regions": [],
        "countries": [
            "United States"
        ],
        "continent": "North America",
        "marker-size": "large",
        "marker-symbol": "triangle",
        "state": "Colorado"
    }
}