{
    "type": "Feature",
    "geometry": {
        "type": "Point",
        "coordinates": [
            -107.05749999999999,
            40.76361111111111
        ]
    },
    "properties": {
        "feet": null,
        "meters": null,
        "latitude": 40.76361111111111,
        "longitude": -107.05749999999999,
        "name": "Sand Mountain North",
        "regions": [],
        "countries": [
            "United States"
        ],
        "continent": "North America",
        "marker-size": "large",
        "marker-symbol": "triangle",
        "state": "Colorado"
    }
}