{
    "type": "Feature",
    "geometry": {
        "type": "Point",
        "coordinates": [
            -106.98138888888889,
            37.57416666666667
        ]
    },
    "properties": {
        "feet": null,
        "meters": null,
        "latitude": 37.57416666666667,
        "longitude": -106.98138888888889,
        "name": "South River Peak",
        "regions": [],
        "countries": [
            "United States"
        ],
        "continent": "North America",
        "marker-size": "large",
        "marker-symbol": "triangle",
        "state": "Colorado"
    }
}