{
    "type": "Feature",
    "geometry": {
        "type": "Point",
        "coordinates": [
            -104.9936101,
            37.3755699
        ]
    },
    "properties": {
        "feet": 13631.0,
        "meters": 4154.728667048683,
        "latitude": 37.3755699,
        "longitude": -104.9936101,
        "name": "West Spanish Peak",
        "countries": [
            "United States"
        ],
        "continent": "North America",
        "marker-size": "large",
        "marker-symbol": "triangle",
        "states": [
            "Colorado"
        ]
    }
}