{
    "type": "Feature",
    "geometry": {
        "type": "Point",
        "coordinates": [
            -104.99333333333334,
            37.37555555555556
        ]
    },
    "properties": {
        "feet": null,
        "meters": null,
        "latitude": 37.37555555555556,
        "longitude": -104.99333333333334,
        "name": "West Spanish Peak",
        "regions": [],
        "countries": [
            "United States"
        ],
        "continent": "North America",
        "marker-size": "large",
        "marker-symbol": "triangle",
        "state": "Colorado"
    }
}