{
  "type": "Feature",
  "geometry": {
    "type": "Point",
    "coordinates": [
      72.4819,
      37.15
    ]
  },
  "properties": {
    "feet": 22057,
    "meters": 6723,
    "latitude": 37.15,
    "longitude": 72.4819,
    "name": "Pik Karl Marx",
    "regions": [
      "Central Asia Ranges",
      "Pamir"
    ],
    "countries": [
      "Tajikistan"
    ],
    "continent": "Asia",
    "marker-size": "large",
    "marker-symbol": "triangle"
  }
}
