{
  "type": "Feature",
  "geometry": {
    "type": "Point",
    "coordinates": [
      72.5222,
      37.1667
    ]
  },
  "properties": {
    "feet": 21358,
    "meters": 6510,
    "latitude": 37.1667,
    "longitude": 72.5222,
    "name": "Pik Engels",
    "countries": [
      "Tajikistan"
    ],
    "continent": "Asia",
    "marker-size": "large",
    "marker-symbol": "triangle"
  }
}
