{
  "type": "Feature",
  "geometry": {
    "type": "Point",
    "coordinates": [
      -71.3225,
      44.2556
    ]
  },
  "properties": {
    "feet": 5384,
    "meters": 1641,
    "latitude": 44.2556,
    "longitude": -71.3225,
    "name": "Mount Monroe",
    "regions": [
      "Appalachian Mountains",
      "White Mountains"
    ],
    "states": [
      "New Hampshire"
    ],
    "countries": [
      "United States"
    ],
    "continent": "North America",
    "marker-size": "medium",
    "marker-symbol": "triangle"
  }
}
